{"title":"Grade 1 English Language Arts","short_title":"grade 1","hierarchy_level":"grade","position":2,"teaser":"Core Knowledge Language Arts Listening and Learning, and Skills","standards":[],"children":[{"title":"Core Knowledge Language Arts, Listening and Learning","short_title":"listening and learning strand","hierarchy_level":"module","position":0,"teaser":"Students build the background knowledge and vocabulary critical to listening and reading comprehension.","standards":["ela-podcast-pk2"],"children":[{"title":"Fables and Stories","short_title":"unit 1","hierarchy_level":"unit","position":0,"teaser":"Students work on vocabulary and comprehension skills, and become familiar with the structure of a story.","standards":["ccss.ela-literacy.l.1.5","ccss.ela-literacy.l.1.5","ccss.ela-literacy.l.1.5a","ccss.ela-literacy.l.1.5a","ccss.ela-literacy.l.1.5c","ccss.ela-literacy.l.1.5c","ccss.ela-literacy.l.1.5d","ccss.ela-literacy.l.1.5d","ccss.ela-literacy.l.1.6","ccss.ela-literacy.l.1.6","ccss.ela-literacy.rl.1.1","ccss.ela-literacy.rl.1.1","ccss.ela-literacy.rl.1.2","ccss.ela-literacy.rl.1.2","ccss.ela-literacy.rl.1.3","ccss.ela-literacy.rl.1.3","ccss.ela-literacy.rl.1.4","ccss.ela-literacy.rl.1.4","ccss.ela-literacy.rl.1.5","ccss.ela-literacy.rl.1.5","ccss.ela-literacy.rl.1.6","ccss.ela-literacy.rl.1.6","ccss.ela-literacy.rl.1.7","ccss.ela-literacy.rl.1.7","ccss.ela-literacy.rl.1.9","ccss.ela-literacy.rl.1.9","ccss.ela-literacy.sl.1.1","ccss.ela-literacy.sl.1.1","ccss.ela-literacy.sl.1.1a","ccss.ela-literacy.sl.1.1a","ccss.ela-literacy.sl.1.1b","ccss.ela-literacy.sl.1.1b","ccss.ela-literacy.sl.1.1c","ccss.ela-literacy.sl.1.1c","ccss.ela-literacy.sl.1.2","ccss.ela-literacy.sl.1.2","ccss.ela-literacy.sl.1.3","ccss.ela-literacy.sl.1.3","ccss.ela-literacy.sl.1.5","ccss.ela-literacy.sl.1.5","ccss.ela-literacy.sl.1.6","ccss.ela-literacy.sl.1.6","ccss.ela-literacy.w.1.1","ccss.ela-literacy.w.1.1","ccss.ela-literacy.w.1.3","ccss.ela-literacy.w.1.3","ccss.ela-literacy.w.1.5","ccss.ela-literacy.w.1.5","ccss.ela-literacy.w.1.6","ccss.ela-literacy.w.1.6","ccss.ela-literacy.w.1.8","ccss.ela-literacy.w.1.8","ela-k2","ela-k2-cg"],"children":[{"title":"The Boy Who Cried Wolf","short_title":"lesson 1","hierarchy_level":"lesson","position":0,"teaser":"Students identify the characters, setting, and plot of \"The Boy Who Cried Wolf\"","standards":[]},{"title":"The Maid and the Milk Pail","short_title":"lesson 2","hierarchy_level":"lesson","position":1,"teaser":"Students identify the characters, setting, and plot of \"The Maid and the Milk Pail\"","standards":[]},{"title":"The Goose and the Golden Eggs","short_title":"lesson 3","hierarchy_level":"lesson","position":2,"teaser":"Students identify the characters, setting, and plot of \"The Goose and the Golden Egg\"","standards":[]},{"title":"The Dog in the Manger","short_title":"lesson 4","hierarchy_level":"lesson","position":3,"teaser":"Using \"The Dog in the Manger,\" students identify what constitutes a fable.","standards":[]},{"title":"The Wolf in Sheep’s Clothing","short_title":"lesson 5","hierarchy_level":"lesson","position":4,"teaser":"Students continue to explore the characteristics of fable using \"The Wolf in Sheep's Clothing\"","standards":[]},{"title":"The Fox and the Grapes","short_title":"lesson 6","hierarchy_level":"lesson","position":5,"teaser":"Students continue to explore the characteristics of fable using \"The Fox and the Grapes\"","standards":[]},{"title":"The Little Half-Chick (Medio Pollito)","short_title":"lesson 7","hierarchy_level":"lesson","position":6,"teaser":"Students study the characteristics of a folktale using “The Little Half-Chick (Medio Pollito)”","standards":[]},{"title":"The Crowded, Noisy House","short_title":"lesson 8","hierarchy_level":"lesson","position":7,"teaser":"Students explore the characteristics of \"The Crowded, Noisy House\"","standards":[]},{"title":"The Tale of Peter Rabbit","short_title":"lesson 9","hierarchy_level":"lesson","position":8,"teaser":"Students describe the characteristics of \"A Tale of Peter Rabbit\"","standards":[]},{"title":"All Stories Are Anansi’s","short_title":"lesson 10","hierarchy_level":"lesson","position":9,"teaser":"Students study the characteristics of a folktale using \"All Stories are Anansi's\"","standards":[]},{"title":"Domain Review","short_title":"lesson 11","hierarchy_level":"lesson","position":10,"teaser":"Review of Fables and Stories","standards":[]},{"title":"Domain Assessment","short_title":"lesson 12","hierarchy_level":"lesson","position":11,"teaser":"Assessment of Fables and Stories","standards":[]},{"title":"Culminating Activities","short_title":"lesson 13","hierarchy_level":"lesson","position":12,"teaser":"Culminating Activities for Fables and Stories","standards":[]}]},{"title":"The Human Body","short_title":"unit 2","hierarchy_level":"unit","position":1,"teaser":"Students are introduced to a network of body systems that work together to keep us alive.","standards":["ccss.ela-literacy.l.1.5","ccss.ela-literacy.l.1.5","ccss.ela-literacy.l.1.5a","ccss.ela-literacy.l.1.5a","ccss.ela-literacy.l.1.5c","ccss.ela-literacy.l.1.5c","ccss.ela-literacy.l.1.6","ccss.ela-literacy.l.1.6","ccss.ela-literacy.ri.1.1","ccss.ela-literacy.ri.1.1","ccss.ela-literacy.ri.1.10","ccss.ela-literacy.ri.1.10","ccss.ela-literacy.ri.1.3","ccss.ela-literacy.ri.1.3","ccss.ela-literacy.ri.1.4","ccss.ela-literacy.ri.1.4","ccss.ela-literacy.ri.1.7","ccss.ela-literacy.ri.1.7","ccss.ela-literacy.ri.1.9","ccss.ela-literacy.ri.1.9","ccss.ela-literacy.sl.1.1","ccss.ela-literacy.sl.1.1","ccss.ela-literacy.sl.1.1a","ccss.ela-literacy.sl.1.1a","ccss.ela-literacy.sl.1.1b","ccss.ela-literacy.sl.1.1b","ccss.ela-literacy.sl.1.1c","ccss.ela-literacy.sl.1.1c","ccss.ela-literacy.sl.1.2","ccss.ela-literacy.sl.1.2","ccss.ela-literacy.sl.1.4","ccss.ela-literacy.sl.1.4","ccss.ela-literacy.sl.1.5","ccss.ela-literacy.sl.1.5","ccss.ela-literacy.sl.1.6","ccss.ela-literacy.sl.1.6","ccss.ela-literacy.w.1.8","ccss.ela-literacy.w.1.8","ela-k2","ela-k2-cg"],"children":[{"title":"Everybody Has a Body","short_title":"lesson 1","hierarchy_level":"lesson","position":0,"teaser":"Students understand that the human body is made up of a network of systems","standards":[]},{"title":"The Body’s Framework","short_title":"lesson 2","hierarchy_level":"lesson","position":1,"teaser":"Students begin to explore those body systems with the skeletal system.","standards":[]},{"title":"Marvelous Moving Muscles","short_title":"lesson 3","hierarchy_level":"lesson","position":2,"teaser":"Students continue their exploration and understanding with the muscular system, including the heart.","standards":[]},{"title":"Chew, Swallow, Squeeze, and Churn","short_title":"lesson 4","hierarchy_level":"lesson","position":3,"teaser":"Students learn about the digestive system.","standards":[]},{"title":"The Body’s Superhighway","short_title":"lesson 5","hierarchy_level":"lesson","position":4,"teaser":"Students learn about the circulatory system.","standards":[]},{"title":"Control Central: The Brain","short_title":"lesson 6","hierarchy_level":"lesson","position":5,"teaser":"Students learn about how the nervous system is the body's control center.","standards":[]},{"title":"Dr. Welbody’s Heroes","short_title":"lesson 7","hierarchy_level":"lesson","position":6,"teaser":"Students learn about the concept of vaccination.","standards":[]},{"title":"Five Keys to Health","short_title":"lesson 8","hierarchy_level":"lesson","position":7,"teaser":"Students learn about how to keep a body healthy, through exercise and vaccination.","standards":[]},{"title":"The Pyramid Pantry","short_title":"lesson 9","hierarchy_level":"lesson","position":8,"teaser":"Students learn about keeping healthy through a balanced diet.","standards":[]},{"title":"What a Complicated Network!","short_title":"lesson 10","hierarchy_level":"lesson","position":9,"teaser":"Students learn about how the body systems function together best when we keep ourselves healthy.","standards":[]},{"title":"Domain Review","short_title":"lesson 11","hierarchy_level":"lesson","position":10,"teaser":"Review of The Human Body","standards":[]},{"title":"Domain Assessment","short_title":"lesson 12","hierarchy_level":"lesson","position":11,"teaser":"Assessment of The Human Body","standards":[]},{"title":"Culminating Activities","short_title":"lesson 13","hierarchy_level":"lesson","position":12,"teaser":"Culminating Activities for The Human Body","standards":[]}]},{"title":"Different Lands, Similar Stories","short_title":"unit 3","hierarchy_level":"unit","position":2,"teaser":"Students study folktales from different countries and cultures that have similar themes and messages.","standards":["ccss.ela-literacy.l.1.5","ccss.ela-literacy.l.1.5","ccss.ela-literacy.l.1.5c","ccss.ela-literacy.l.1.5c","ccss.ela-literacy.l.1.6","ccss.ela-literacy.l.1.6","ccss.ela-literacy.rl.1.1","ccss.ela-literacy.rl.1.1","ccss.ela-literacy.rl.1.2","ccss.ela-literacy.rl.1.2","ccss.ela-literacy.rl.1.3","ccss.ela-literacy.rl.1.3","ccss.ela-literacy.rl.1.4","ccss.ela-literacy.rl.1.4","ccss.ela-literacy.rl.1.5","ccss.ela-literacy.rl.1.5","ccss.ela-literacy.rl.1.7","ccss.ela-literacy.rl.1.7","ccss.ela-literacy.rl.1.9","ccss.ela-literacy.rl.1.9","ccss.ela-literacy.sl.1.1","ccss.ela-literacy.sl.1.1","ccss.ela-literacy.sl.1.1a","ccss.ela-literacy.sl.1.1a","ccss.ela-literacy.sl.1.1b","ccss.ela-literacy.sl.1.1b","ccss.ela-literacy.sl.1.1c","ccss.ela-literacy.sl.1.1c","ccss.ela-literacy.sl.1.2","ccss.ela-literacy.sl.1.2","ccss.ela-literacy.sl.1.4","ccss.ela-literacy.sl.1.4","ccss.ela-literacy.sl.1.5","ccss.ela-literacy.sl.1.5","ccss.ela-literacy.sl.1.6","ccss.ela-literacy.sl.1.6","ccss.ela-literacy.w.1.2","ccss.ela-literacy.w.1.2","ela-k2","ela-k2-cg"],"children":[{"title":"Cinderella","short_title":"lesson 1","hierarchy_level":"lesson","position":0,"teaser":"Students study the components of a story using \"Cinderella\"","standards":[]},{"title":"The Girl with the Red Slippers","short_title":"lesson 2","hierarchy_level":"lesson","position":1,"teaser":"Students explore similarities between \"Cinderella\" and \"The Girl with the Red Slippers\"","standards":[]},{"title":"Billy Beg","short_title":"lesson 3","hierarchy_level":"lesson","position":2,"teaser":"Students continue to explore fiction using \"Billy Beg\"","standards":[]},{"title":"Tom Thumb","short_title":"lesson 4","hierarchy_level":"lesson","position":3,"teaser":"Students continue to learn about characters, plot, and setting using \"Tom Thumb\"","standards":[]},{"title":"Thumbelina","short_title":"lesson 5","hierarchy_level":"lesson","position":4,"teaser":"Students identify similarities between previous stories and \"Thumbelina\"","standards":[]},{"title":"Issun Boshi: One-Inch Boy","short_title":"lesson 6","hierarchy_level":"lesson","position":5,"teaser":"Students identify similarities between previous stories and \"Issun Boshi: One-inch Boy\"","standards":[]},{"title":"Little Red Riding Hood","short_title":"lesson 7","hierarchy_level":"lesson","position":6,"teaser":"Students explore \"Little Red Riding Hood,\" examining character, plot, and setting.","standards":[]},{"title":"Hu Gu Po","short_title":"lesson 8","hierarchy_level":"lesson","position":7,"teaser":"Students describe the characters, plot, and setting of “Hu Gu Po”","standards":[]},{"title":"Tselane","short_title":"lesson 9","hierarchy_level":"lesson","position":8,"teaser":"Students dive into \"Tselane\" and discuss how different cultures address similar themes","standards":[]},{"title":"Domain Review","short_title":"lesson 10","hierarchy_level":"lesson","position":9,"teaser":"Review of Different Lands, Similar Stories","standards":[]},{"title":"Domain Assessment","short_title":"lesson 11","hierarchy_level":"lesson","position":10,"teaser":"Assessment of Different Lands, Similar Stories","standards":[]},{"title":"Culminating Activities","short_title":"lesson 12","hierarchy_level":"lesson","position":11,"teaser":"Culminating Activities for Different Lands, Similar Stories","standards":[]}]},{"title":"Early World Civilizations","short_title":"unit 4","hierarchy_level":"unit","position":3,"teaser":"Students explore how and where civilizations, governments, writing and religion form.","standards":["ccss.ela-literacy.l.1.5c","ccss.ela-literacy.l.1.5c","ccss.ela-literacy.l.1.6","ccss.ela-literacy.l.1.6","ccss.ela-literacy.ri.1.1","ccss.ela-literacy.ri.1.1","ccss.ela-literacy.ri.1.10","ccss.ela-literacy.ri.1.10","ccss.ela-literacy.ri.1.2","ccss.ela-literacy.ri.1.2","ccss.ela-literacy.ri.1.3","ccss.ela-literacy.ri.1.3","ccss.ela-literacy.ri.1.4","ccss.ela-literacy.ri.1.4","ccss.ela-literacy.ri.1.7","ccss.ela-literacy.ri.1.7","ccss.ela-literacy.ri.1.9","ccss.ela-literacy.ri.1.9","ccss.ela-literacy.rl.1.3","ccss.ela-literacy.rl.1.3","ccss.ela-literacy.rl.1.6","ccss.ela-literacy.rl.1.6","ccss.ela-literacy.sl.1.1","ccss.ela-literacy.sl.1.1","ccss.ela-literacy.sl.1.1a","ccss.ela-literacy.sl.1.1a","ccss.ela-literacy.sl.1.1b","ccss.ela-literacy.sl.1.1b","ccss.ela-literacy.sl.1.1c","ccss.ela-literacy.sl.1.1c","ccss.ela-literacy.sl.1.2","ccss.ela-literacy.sl.1.2","ccss.ela-literacy.sl.1.3","ccss.ela-literacy.sl.1.3","ccss.ela-literacy.sl.1.4","ccss.ela-literacy.sl.1.4","ccss.ela-literacy.sl.1.5","ccss.ela-literacy.sl.1.5","ccss.ela-literacy.sl.1.6","ccss.ela-literacy.sl.1.6","ccss.ela-literacy.w.1.5","ccss.ela-literacy.w.1.5","ccss.ela-literacy.w.1.8","ccss.ela-literacy.w.1.8","ela-k2","ela-k2-cg"],"children":[{"title":"A Father and His Son in Mesopotamia","short_title":"lesson 1","hierarchy_level":"lesson","position":0,"teaser":"Students learn, through an historical fiction vignette in Mesopotamia, how rivers support civilizations.","standards":[]},{"title":"Writing in Mesopotamia","short_title":"lesson 2","hierarchy_level":"lesson","position":1,"teaser":"Students explore reading, writing, and laws in Mesopotamia, examining the Code of Hammurabi","standards":[]},{"title":"The Religion of Babylon","short_title":"lesson 3","hierarchy_level":"lesson","position":2,"teaser":"Students learn about the significance of gods, ziggurats, and priests in ancient Mesopotamia","standards":[]},{"title":"The Hanging Gardens of Babylon","short_title":"lesson 4","hierarchy_level":"lesson","position":3,"teaser":"Students understand the importance of the Tigris and Euphrates rivers as the Cradle of Civilization","standards":[]},{"title":"People of the Nile","short_title":"lesson 5","hierarchy_level":"lesson","position":4,"teaser":"Students continue to learn to identify geographic locations on maps, turning their focus to Egypt.","standards":[]},{"title":"Writing in Ancient Egypt","short_title":"lesson 6","hierarchy_level":"lesson","position":5,"teaser":"Students learn, through studying Egyptian hieroglyphs, how written language is important to civilizations","standards":[]},{"title":"Amon-Ra and the Gods of Ancient Egypt","short_title":"lesson 7","hierarchy_level":"lesson","position":6,"teaser":"Students will be able to locate Egypt on a map and explore the gods of ancient Egypt","standards":[]},{"title":"Approaching the Great Pyramid","short_title":"lesson 8","hierarchy_level":"lesson","position":7,"teaser":"Students will study the pyramids.","standards":[]},{"title":"The Sphinx","short_title":"lesson 9","hierarchy_level":"lesson","position":8,"teaser":"Students will learn that Egypt is located in the desert of Africa, and explore the mystery of the Sphinx","standards":[]},{"title":"The Story of Hatshepsut","short_title":"lesson 10","hierarchy_level":"lesson","position":9,"teaser":"Students will learn about Hatshepsut, a female pharaoh of ancient Egypt","standards":[]},{"title":"Tutankhamun, The Golden Pharaoh, Part I","short_title":"lesson 11","hierarchy_level":"lesson","position":10,"teaser":"Students will learn about archaeology through the exploration of King Tut","standards":[]},{"title":"Tutankhamun, The Golden Pharaoh, Part II","short_title":"lesson 12","hierarchy_level":"lesson","position":11,"teaser":"Students will continue to learn about King Tutankhamun","standards":[]},{"title":"Three World Religions","short_title":"lesson 13","hierarchy_level":"lesson","position":12,"teaser":"Students will identify Judaism, Christianity, and Islam as major monotheistic world religions","standards":[]},{"title":"Judaism","short_title":"lesson 14","hierarchy_level":"lesson","position":13,"teaser":"Students study the origins of Judaism.","standards":[]},{"title":"Christianity","short_title":"lesson 15","hierarchy_level":"lesson","position":14,"teaser":"Students study the origins of Christianity","standards":[]},{"title":"Islam","short_title":"lesson 16","hierarchy_level":"lesson","position":15,"teaser":"Students study the origins of Islam","standards":[]},{"title":"Domain Review","short_title":"lesson 17","hierarchy_level":"lesson","position":16,"teaser":"Review of Early World Civilizations","standards":[]},{"title":"Domain Assessment","short_title":"lesson 18","hierarchy_level":"lesson","position":17,"teaser":"Assessment of Early World Civilizations","standards":[]},{"title":"Culminating Activities","short_title":"lesson 19","hierarchy_level":"lesson","position":18,"teaser":"Culminating Activities for Early World Civilizations","standards":[]}]},{"title":"Early American Civilizations","short_title":"unit 5","hierarchy_level":"unit","position":4,"teaser":"Students will examine the fundamental features of the Maya, Aztec, and Inca","standards":["ccss.ela-literacy.l.1.5","ccss.ela-literacy.l.1.5","ccss.ela-literacy.l.1.5a","ccss.ela-literacy.l.1.5a","ccss.ela-literacy.l.1.5c","ccss.ela-literacy.l.1.5c","ccss.ela-literacy.l.1.5d","ccss.ela-literacy.l.1.5d","ccss.ela-literacy.l.1.6","ccss.ela-literacy.l.1.6","ccss.ela-literacy.ri.1.1","ccss.ela-literacy.ri.1.1","ccss.ela-literacy.ri.1.10","ccss.ela-literacy.ri.1.10","ccss.ela-literacy.ri.1.2","ccss.ela-literacy.ri.1.2","ccss.ela-literacy.ri.1.3","ccss.ela-literacy.ri.1.3","ccss.ela-literacy.ri.1.4","ccss.ela-literacy.ri.1.4","ccss.ela-literacy.ri.1.6","ccss.ela-literacy.ri.1.6","ccss.ela-literacy.ri.1.7","ccss.ela-literacy.ri.1.7","ccss.ela-literacy.ri.1.9","ccss.ela-literacy.ri.1.9","ccss.ela-literacy.sl.1.1","ccss.ela-literacy.sl.1.1","ccss.ela-literacy.sl.1.1a","ccss.ela-literacy.sl.1.1a","ccss.ela-literacy.sl.1.1b","ccss.ela-literacy.sl.1.1b","ccss.ela-literacy.sl.1.1c","ccss.ela-literacy.sl.1.1c","ccss.ela-literacy.sl.1.2","ccss.ela-literacy.sl.1.2","ccss.ela-literacy.sl.1.3","ccss.ela-literacy.sl.1.3","ccss.ela-literacy.sl.1.4","ccss.ela-literacy.sl.1.4","ccss.ela-literacy.sl.1.5","ccss.ela-literacy.sl.1.5","ccss.ela-literacy.sl.1.6","ccss.ela-literacy.sl.1.6","ccss.ela-literacy.w.1.2","ccss.ela-literacy.w.1.2","ccss.ela-literacy.w.1.5","ccss.ela-literacy.w.1.5","ccss.ela-literacy.w.1.8","ccss.ela-literacy.w.1.8","ela-k2","ela-k2-cg"],"children":[{"title":"The Maya: A Harvest and a Hurricane","short_title":"lesson 1","hierarchy_level":"lesson","position":0,"teaser":"Students will study the Mayan society, including farming and family","standards":[]},{"title":"The Maya: Journey to Baakal","short_title":"lesson 2","hierarchy_level":"lesson","position":1,"teaser":"Students will understand where the Mayan Empire was located","standards":[]},{"title":"The Maya: King Pakal’s Tomb","short_title":"lesson 3","hierarchy_level":"lesson","position":2,"teaser":"Students will explore the leadership structure of the Mayan Empire","standards":[]},{"title":"The Maya: The Festival of the First Star","short_title":"lesson 4","hierarchy_level":"lesson","position":3,"teaser":"Students will explore the how the stars and planets impacted the Mayan calendar","standards":[]},{"title":"The Aztec: The Legend of the Eagle and the Serpent","short_title":"lesson 5","hierarchy_level":"lesson","position":4,"teaser":"Students will shift to studying the Aztecs and their civilization","standards":[]},{"title":"The Aztec: The Floating Gardens of Xochimilco","short_title":"lesson 6","hierarchy_level":"lesson","position":5,"teaser":"Students will understand where the Aztec Empire was located","standards":[]},{"title":"The Aztec: In the Palace of an Emperor","short_title":"lesson 7","hierarchy_level":"lesson","position":6,"teaser":"Students will study the emperors of the Aztecs and its capitol","standards":[]},{"title":"The Aztec: Cortés’s Letter","short_title":"lesson 8","hierarchy_level":"lesson","position":7,"teaser":"Students will continue to learn about the Aztecs, where they were located, and what they believed.","standards":[]},{"title":"The Inca: Who Were the Inca?","short_title":"lesson 9","hierarchy_level":"lesson","position":8,"teaser":"Students will begin to explore the Incas and where they lived.","standards":[]},{"title":"The Inca: The Runner","short_title":"lesson 10","hierarchy_level":"lesson","position":9,"teaser":"Students will learn about how the Inca lived.","standards":[]},{"title":"The Inca: Machu Picchu— A Lucky Discovery","short_title":"lesson 11","hierarchy_level":"lesson","position":10,"teaser":"Students will learn about Machu Picchu and archaeology","standards":[]},{"title":"Domain Review","short_title":"lesson 12","hierarchy_level":"lesson","position":11,"teaser":"Review of Early American Civilizations","standards":[]},{"title":"Domain Assessment","short_title":"lesson 13","hierarchy_level":"lesson","position":12,"teaser":"Assessment of Early American Civilizations","standards":[]},{"title":"Culminating Activities","short_title":"lesson 14","hierarchy_level":"lesson","position":13,"teaser":"Culminating Activities for Early American Civilizations","standards":[]}]},{"title":"Astronomy","short_title":"unit 6","hierarchy_level":"unit","position":5,"teaser":"Students will study our place in the solar system","standards":["ccss.ela-literacy.l.1.5","ccss.ela-literacy.l.1.5","ccss.ela-literacy.l.1.5a","ccss.ela-literacy.l.1.5a","ccss.ela-literacy.l.1.5c","ccss.ela-literacy.l.1.5c","ccss.ela-literacy.l.1.5d","ccss.ela-literacy.l.1.5d","ccss.ela-literacy.l.1.6","ccss.ela-literacy.l.1.6","ccss.ela-literacy.ri.1.1","ccss.ela-literacy.ri.1.1","ccss.ela-literacy.ri.1.10","ccss.ela-literacy.ri.1.10","ccss.ela-literacy.ri.1.3","ccss.ela-literacy.ri.1.3","ccss.ela-literacy.ri.1.4","ccss.ela-literacy.ri.1.4","ccss.ela-literacy.ri.1.7","ccss.ela-literacy.ri.1.7","ccss.ela-literacy.ri.1.9","ccss.ela-literacy.ri.1.9","ccss.ela-literacy.rl.1.5","ccss.ela-literacy.rl.1.5","ccss.ela-literacy.sl.1.1","ccss.ela-literacy.sl.1.1","ccss.ela-literacy.sl.1.1a","ccss.ela-literacy.sl.1.1a","ccss.ela-literacy.sl.1.1b","ccss.ela-literacy.sl.1.1b","ccss.ela-literacy.sl.1.1c","ccss.ela-literacy.sl.1.1c","ccss.ela-literacy.sl.1.2","ccss.ela-literacy.sl.1.2","ccss.ela-literacy.sl.1.3","ccss.ela-literacy.sl.1.3","ccss.ela-literacy.sl.1.4","ccss.ela-literacy.sl.1.4","ccss.ela-literacy.sl.1.5","ccss.ela-literacy.sl.1.5","ccss.ela-literacy.sl.1.6","ccss.ela-literacy.sl.1.6","ccss.ela-literacy.w.1.8","ccss.ela-literacy.w.1.8","ela-k2","ela-k2-cg"],"children":[{"title":"Introduction to the Sun and Space","short_title":"lesson 1","hierarchy_level":"lesson","position":0,"teaser":"Students will begin to explore the sun and how it supports life","standards":[]},{"title":"The Earth and the Sun","short_title":"lesson 2","hierarchy_level":"lesson","position":1,"teaser":"Students will begin to understand the Earth, its rotation, and its connection to day and night.","standards":[]},{"title":"Stars","short_title":"lesson 3","hierarchy_level":"lesson","position":2,"teaser":"Students will study the sun as a star.","standards":[]},{"title":"Stargazing and Constellations","short_title":"lesson 4","hierarchy_level":"lesson","position":3,"teaser":"Students will learn about how telescopes help us to understand the moon, stars, and constellations.","standards":[]},{"title":"The Moon","short_title":"lesson 5","hierarchy_level":"lesson","position":4,"teaser":"Students will study the four phases of the moon.","standards":[]},{"title":"History of Space Exploration and Astronauts","short_title":"lesson 6","hierarchy_level":"lesson","position":5,"teaser":"Students will study astronauts.","standards":[]},{"title":"Exploration of the Moon","short_title":"lesson 7","hierarchy_level":"lesson","position":6,"teaser":"Students will learn about how astronauts landed on the moon.","standards":[]},{"title":"The Solar System, Part I","short_title":"lesson 8","hierarchy_level":"lesson","position":7,"teaser":"Students will learn about the planets in our solar system","standards":[]},{"title":"The Solar System, Part II","short_title":"lesson 9","hierarchy_level":"lesson","position":8,"teaser":"Students will continue to learn about our solar system.","standards":[]},{"title":"Domain Review","short_title":"lesson 10","hierarchy_level":"lesson","position":9,"teaser":"Review of Astronomy","standards":[]},{"title":"Domain Assessment","short_title":"lesson 11","hierarchy_level":"lesson","position":10,"teaser":"Assessment of Astronomy","standards":[]},{"title":"Culminating Activities","short_title":"lesson 12","hierarchy_level":"lesson","position":11,"teaser":"Culminating Activities for Astronomy","standards":[]}]},{"title":"The History of the Earth","short_title":"unit 7","hierarchy_level":"unit","position":6,"teaser":"Students will learn about the geographical features of the Earth, from the layers to fascinating functions .","standards":["ccss.ela-literacy.l.1.5","ccss.ela-literacy.l.1.5","ccss.ela-literacy.l.1.5c","ccss.ela-literacy.l.1.5c","ccss.ela-literacy.l.1.6","ccss.ela-literacy.l.1.6","ccss.ela-literacy.ri.1.1","ccss.ela-literacy.ri.1.1","ccss.ela-literacy.ri.1.10","ccss.ela-literacy.ri.1.10","ccss.ela-literacy.ri.1.3","ccss.ela-literacy.ri.1.3","ccss.ela-literacy.ri.1.4","ccss.ela-literacy.ri.1.4","ccss.ela-literacy.ri.1.7","ccss.ela-literacy.ri.1.7","ccss.ela-literacy.ri.1.9","ccss.ela-literacy.ri.1.9","ccss.ela-literacy.sl.1.1","ccss.ela-literacy.sl.1.1","ccss.ela-literacy.sl.1.1a","ccss.ela-literacy.sl.1.1a","ccss.ela-literacy.sl.1.1b","ccss.ela-literacy.sl.1.1b","ccss.ela-literacy.sl.1.1c","ccss.ela-literacy.sl.1.1c","ccss.ela-literacy.sl.1.2","ccss.ela-literacy.sl.1.2","ccss.ela-literacy.sl.1.3","ccss.ela-literacy.sl.1.3","ccss.ela-literacy.sl.1.4","ccss.ela-literacy.sl.1.4","ccss.ela-literacy.sl.1.5","ccss.ela-literacy.sl.1.5","ccss.ela-literacy.sl.1.6","ccss.ela-literacy.sl.1.6","ccss.ela-literacy.w.1.1","ccss.ela-literacy.w.1.1","ccss.ela-literacy.w.1.2","ccss.ela-literacy.w.1.2","ccss.ela-literacy.w.1.8","ccss.ela-literacy.w.1.8","ela-k2","ela-k2-cg"],"children":[{"title":"Our Home, Earth","short_title":"lesson 1","hierarchy_level":"lesson","position":0,"teaser":"Students will learn about oceans and continents, and how scientists grow our understanding.","standards":[]},{"title":"The Earth Inside-Out, Part I","short_title":"lesson 2","hierarchy_level":"lesson","position":1,"teaser":"Students focus on the layers of the Earth, including the crust.","standards":[]},{"title":"The Earth Inside-Out, Part II","short_title":"lesson 3","hierarchy_level":"lesson","position":2,"teaser":"Students learn about the Earth's mantle, volcanoes, and how heat, pressure and time change the Earth","standards":[]},{"title":"The Earth Inside-Out, Part III","short_title":"lesson 4","hierarchy_level":"lesson","position":3,"teaser":"Students will explore volcanoes and geysers.","standards":[]},{"title":"Minerals","short_title":"lesson 5","hierarchy_level":"lesson","position":4,"teaser":"Students learn about the common minerals of the Earth.","standards":[]},{"title":"The Three Types of Rocks","short_title":"lesson 6","hierarchy_level":"lesson","position":5,"teaser":"Students identify the three types of rocks.","standards":[]},{"title":"Fossils","short_title":"lesson 7","hierarchy_level":"lesson","position":6,"teaser":"Students will learn about fossils.","standards":[]},{"title":"Dinosaurs","short_title":"lesson 8","hierarchy_level":"lesson","position":7,"teaser":"Students will learn about the dinosaurs","standards":[]},{"title":"Domain Review","short_title":"lesson 9","hierarchy_level":"lesson","position":8,"teaser":"Review of The History of the Earth","standards":[]},{"title":"Domain Assessment","short_title":"lesson 10","hierarchy_level":"lesson","position":9,"teaser":"Assessment of The History of the Earth","standards":[]},{"title":"Culminating Activities","short_title":"lesson 11","hierarchy_level":"lesson","position":10,"teaser":"Culminating Activities for The History of the Earth","standards":[]}]},{"title":"Animals and Habitats","short_title":"unit 8","hierarchy_level":"unit","position":7,"teaser":"Students will study the interconnectedness of all living things in the natural world, with a focus on habitat.","standards":["ccss.ela-literacy.l.1.5","ccss.ela-literacy.l.1.5","ccss.ela-literacy.l.1.5a","ccss.ela-literacy.l.1.5a","ccss.ela-literacy.l.1.5b","ccss.ela-literacy.l.1.5b","ccss.ela-literacy.l.1.5c","ccss.ela-literacy.l.1.5c","ccss.ela-literacy.l.1.6","ccss.ela-literacy.l.1.6","ccss.ela-literacy.ri.1.1","ccss.ela-literacy.ri.1.1","ccss.ela-literacy.ri.1.10","ccss.ela-literacy.ri.1.10","ccss.ela-literacy.ri.1.3","ccss.ela-literacy.ri.1.3","ccss.ela-literacy.ri.1.4","ccss.ela-literacy.ri.1.4","ccss.ela-literacy.ri.1.7","ccss.ela-literacy.ri.1.7","ccss.ela-literacy.ri.1.8","ccss.ela-literacy.ri.1.8","ccss.ela-literacy.ri.1.9","ccss.ela-literacy.ri.1.9","ccss.ela-literacy.sl.1.1","ccss.ela-literacy.sl.1.1","ccss.ela-literacy.sl.1.1a","ccss.ela-literacy.sl.1.1a","ccss.ela-literacy.sl.1.1b","ccss.ela-literacy.sl.1.1b","ccss.ela-literacy.sl.1.1c","ccss.ela-literacy.sl.1.1c","ccss.ela-literacy.sl.1.2","ccss.ela-literacy.sl.1.2","ccss.ela-literacy.sl.1.4","ccss.ela-literacy.sl.1.4","ccss.ela-literacy.sl.1.5","ccss.ela-literacy.sl.1.5","ccss.ela-literacy.sl.1.6","ccss.ela-literacy.sl.1.6","ccss.ela-literacy.w.1.1","ccss.ela-literacy.w.1.1","ccss.ela-literacy.w.1.8","ccss.ela-literacy.w.1.8","ela-k2","ela-k2-cg"],"children":[{"title":"What is a Habitat?","short_title":"lesson 1","hierarchy_level":"lesson","position":0,"teaser":"Students will learn about what a habitat is.","standards":[]},{"title":"Animals of the Arctic Habitat","short_title":"lesson 2","hierarchy_level":"lesson","position":1,"teaser":"Students will explore different habitats, beginning with the Arctic Tundra and Arctic Ocean","standards":[]},{"title":"Animals of the Sonoran Desert Habitat","short_title":"lesson 3","hierarchy_level":"lesson","position":2,"teaser":"Students learn about the desert habitats, and they will classify animals according to foods they eat","standards":[]},{"title":"Animals of the East African Savanna Habitat","short_title":"lesson 4","hierarchy_level":"lesson","position":3,"teaser":"Students will learn about the grassland habitat.","standards":[]},{"title":"Animals of the Temperate Deciduous Forest Habitat","short_title":"lesson 5","hierarchy_level":"lesson","position":4,"teaser":"Students will learn about the animals in the temperate deciduous forest habitat","standards":[]},{"title":"Animals of the Tropical Rainforest Habitat","short_title":"lesson 6","hierarchy_level":"lesson","position":5,"teaser":"Students will learn about adaptations and the tropical rainforest habitat","standards":[]},{"title":"Animals of the Freshwater Habitat","short_title":"lesson 7","hierarchy_level":"lesson","position":6,"teaser":"Students will learn how to discern between fresh and saltwater habitats, with a focus on freshwater","standards":[]},{"title":"Animals of the Saltwater Habitat","short_title":"lesson 8","hierarchy_level":"lesson","position":7,"teaser":"Students will study the diversity of the ocean.","standards":[]},{"title":"Habitat Destruction and Endangered Species","short_title":"lesson 9","hierarchy_level":"lesson","position":8,"teaser":"Students will focus on how habitat destruction can cause extinction.","standards":[]},{"title":"Domain Review","short_title":"lesson 10","hierarchy_level":"lesson","position":9,"teaser":"Review of Animals and Habitats","standards":[]},{"title":"Domain Assessment","short_title":"lesson 11","hierarchy_level":"lesson","position":10,"teaser":"Assessment of Animals and Habitats","standards":[]},{"title":"Culminating Activities","short_title":"lesson 12","hierarchy_level":"lesson","position":11,"teaser":"Culminating Activities for Animals and Habitats","standards":[]}]},{"title":"Fairy Tales","short_title":"unit 9","hierarchy_level":"unit","position":8,"teaser":"Students will begin to learn about how fairy tales are different from other types of fiction","standards":["ccss.ela-literacy.l.1.5","ccss.ela-literacy.l.1.5","ccss.ela-literacy.l.1.5a","ccss.ela-literacy.l.1.5a","ccss.ela-literacy.l.1.5c","ccss.ela-literacy.l.1.5c","ccss.ela-literacy.l.1.5d","ccss.ela-literacy.l.1.5d","ccss.ela-literacy.l.1.6","ccss.ela-literacy.l.1.6","ccss.ela-literacy.rl.1.1","ccss.ela-literacy.rl.1.1","ccss.ela-literacy.rl.1.2","ccss.ela-literacy.rl.1.2","ccss.ela-literacy.rl.1.3","ccss.ela-literacy.rl.1.3","ccss.ela-literacy.rl.1.4","ccss.ela-literacy.rl.1.4","ccss.ela-literacy.rl.1.5","ccss.ela-literacy.rl.1.5","ccss.ela-literacy.rl.1.7","ccss.ela-literacy.rl.1.7","ccss.ela-literacy.rl.1.9","ccss.ela-literacy.rl.1.9","ccss.ela-literacy.sl.1.1","ccss.ela-literacy.sl.1.1","ccss.ela-literacy.sl.1.1a","ccss.ela-literacy.sl.1.1a","ccss.ela-literacy.sl.1.1b","ccss.ela-literacy.sl.1.1b","ccss.ela-literacy.sl.1.1c","ccss.ela-literacy.sl.1.1c","ccss.ela-literacy.sl.1.2","ccss.ela-literacy.sl.1.2","ccss.ela-literacy.sl.1.3","ccss.ela-literacy.sl.1.3","ccss.ela-literacy.sl.1.4","ccss.ela-literacy.sl.1.4","ccss.ela-literacy.sl.1.5","ccss.ela-literacy.sl.1.5","ccss.ela-literacy.sl.1.6","ccss.ela-literacy.sl.1.6","ccss.ela-literacy.w.1.1","ccss.ela-literacy.w.1.1","ccss.ela-literacy.w.1.3","ccss.ela-literacy.w.1.3","ccss.ela-literacy.w.1.5","ccss.ela-literacy.w.1.5","ccss.ela-literacy.w.1.6","ccss.ela-literacy.w.1.6","ccss.ela-literacy.w.1.7","ccss.ela-literacy.w.1.7","ccss.ela-literacy.w.1.8","ccss.ela-literacy.w.1.8","ela-k2","ela-k2-cg"],"children":[{"title":"Sleeping Beauty","short_title":"lesson 1","hierarchy_level":"lesson","position":0,"teaser":"Students will use \"Sleeping Beauty\" to study common characteristics of fairy tales","standards":[]},{"title":"Rumpelstiltskin","short_title":"lesson 2","hierarchy_level":"lesson","position":1,"teaser":"Students will use \"Rumpelstiltskin\" to study common characteristics of fairy tales","standards":[]},{"title":"Rapunzel","short_title":"lesson 3","hierarchy_level":"lesson","position":2,"teaser":"Students learn about \"Rapunzel,\" and compare different adaptations of fairy tales","standards":[]},{"title":"The Frog Prince, Part I","short_title":"lesson 4","hierarchy_level":"lesson","position":3,"teaser":"Students will become familiar with \"The Frog Prince\" fairy tale","standards":[]},{"title":"The Frog Prince, Part II","short_title":"lesson 5","hierarchy_level":"lesson","position":4,"teaser":"Students will continue to study fairy tales using \"The Frog Prince\"","standards":[]},{"title":"Hansel and Gretel, Part I","short_title":"lesson 6","hierarchy_level":"lesson","position":5,"teaser":"Students will continue to learn about the elements of fairy tales using \"Hansel and Gretel\"","standards":[]},{"title":"Hansel and Gretel, Part II","short_title":"lesson 7","hierarchy_level":"lesson","position":6,"teaser":"Students will continue to work with \"Hansel and Gretel\"","standards":[]},{"title":"Jack and the Beanstalk, Part I","short_title":"lesson 8","hierarchy_level":"lesson","position":7,"teaser":"Students will learn about the fairy tale elements of \"Jack and the Beanstalk\"","standards":[]},{"title":"Jack and the Beanstalk, Part II","short_title":"lesson 9","hierarchy_level":"lesson","position":8,"teaser":"Students will continue to read \"Jack and the Beanstalk,\" identifying the common characteristics of fairy tales","standards":[]},{"title":"Domain Review","short_title":"lesson 10","hierarchy_level":"lesson","position":9,"teaser":"Review of Fairy Tales","standards":[]},{"title":"Domain Assessment","short_title":"lesson 11","hierarchy_level":"lesson","position":10,"teaser":"Assessment of Fairy Tales","standards":[]},{"title":"Culminating Activities","short_title":"lesson 12","hierarchy_level":"lesson","position":11,"teaser":"Culminating Activities for Fairy Tales","standards":[]}]},{"title":"A New Nation: American Independence","short_title":"unit 10","hierarchy_level":"unit","position":9,"teaser":"Students study how the stories of historical figures contributed to the formation of the United States.","standards":["ccss.ela-literacy.l.1.5","ccss.ela-literacy.l.1.5a","ccss.ela-literacy.l.1.5c","ccss.ela-literacy.l.1.6","ccss.ela-literacy.ri.1.1","ccss.ela-literacy.ri.1.10","ccss.ela-literacy.ri.1.2","ccss.ela-literacy.ri.1.3","ccss.ela-literacy.ri.1.4","ccss.ela-literacy.ri.1.6","ccss.ela-literacy.ri.1.7","ccss.ela-literacy.ri.1.8","ccss.ela-literacy.ri.1.9","ccss.ela-literacy.sl.1.1","ccss.ela-literacy.sl.1.1a","ccss.ela-literacy.sl.1.1b","ccss.ela-literacy.sl.1.1c","ccss.ela-literacy.sl.1.2","ccss.ela-literacy.sl.1.3","ccss.ela-literacy.sl.1.4","ccss.ela-literacy.sl.1.5","ccss.ela-literacy.sl.1.6","ccss.ela-literacy.w.1.2","ccss.ela-literacy.w.1.5","ccss.ela-literacy.w.1.7","ccss.ela-literacy.w.1.8","ela-k2","ela-k2-cg"],"children":[{"title":"The New World","short_title":"lesson 1","hierarchy_level":"lesson","position":0,"teaser":"Students study how the United States came to be, including indentured servitude, colonization, and independence.","standards":[]},{"title":"A Taxing Time: The Boston Tea Party","short_title":"lesson 2","hierarchy_level":"lesson","position":1,"teaser":"Students learn about the thirteen colonies and the Boston Tea Party","standards":[]},{"title":"The Shot Heard Round the World","short_title":"lesson 3","hierarchy_level":"lesson","position":2,"teaser":"Students learn about Paul Revere's Ride","standards":[]},{"title":"Declaring Independence","short_title":"lesson 4","hierarchy_level":"lesson","position":3,"teaser":"Students learn about the contributions of the Founding Fathers","standards":[]},{"title":"The Legend of Betsy Ross","short_title":"lesson 5","hierarchy_level":"lesson","position":4,"teaser":"Students learn about the legend of Betsy Ross and the flag","standards":[]},{"title":"George Washington, Commander in Chief","short_title":"lesson 6","hierarchy_level":"lesson","position":5,"teaser":"Students learn about the contributions of George Washington as a military commander","standards":[]},{"title":"Will This War Never End?","short_title":"lesson 7","hierarchy_level":"lesson","position":6,"teaser":"Students learn about the contributions of George Washington as a military commander","standards":[]},{"title":"A Young Nation is Born","short_title":"lesson 8","hierarchy_level":"lesson","position":7,"teaser":"Students learn about the contributions of George Washington as a president","standards":[]},{"title":"Never Leave Until Tomorrow What You Can Do Today","short_title":"lesson 9","hierarchy_level":"lesson","position":8,"teaser":"Students learn about Benjamin Franklin.","standards":[]},{"title":"Building a Nation with Words and Ideas","short_title":"lesson 10","hierarchy_level":"lesson","position":9,"teaser":"Students learn about the contributions of Thomas Jefferson","standards":[]},{"title":"Liberty and Justice for ALL?","short_title":"lesson 11","hierarchy_level":"lesson","position":10,"teaser":"Students explore the roles of African Americans, Native Americans, and women in the early United States","standards":[]},{"title":"What Do a Flag, a Bell, and an Eagle Have in Common?","short_title":"lesson 12","hierarchy_level":"lesson","position":11,"teaser":"Students learn about symbols of the nation.","standards":[]},{"title":"Domain Review","short_title":"lesson 13","hierarchy_level":"lesson","position":12,"teaser":"Review of A New Nation: American Independence","standards":[]},{"title":"Domain Assessment","short_title":"lesson 14","hierarchy_level":"lesson","position":13,"teaser":"Assessment of A New Nation: American Independence","standards":[]},{"title":"Culminating Activities","short_title":"lesson 15","hierarchy_level":"lesson","position":14,"teaser":"Culminating Activities for A New Nation: American Independence","standards":[]}]},{"title":"Frontier Explorers","short_title":"unit 11","hierarchy_level":"unit","position":10,"teaser":"Students learn about  early westward expansion of the United States.","standards":["ccss.ela-literacy.l.1.5","ccss.ela-literacy.l.1.5a","ccss.ela-literacy.l.1.5c","ccss.ela-literacy.l.1.6","ccss.ela-literacy.ri.1.1","ccss.ela-literacy.ri.1.10","ccss.ela-literacy.ri.1.3","ccss.ela-literacy.ri.1.4","ccss.ela-literacy.ri.1.6","ccss.ela-literacy.ri.1.7","ccss.ela-literacy.ri.1.9","ccss.ela-literacy.sl.1.1","ccss.ela-literacy.sl.1.1a","ccss.ela-literacy.sl.1.1b","ccss.ela-literacy.sl.1.1c","ccss.ela-literacy.sl.1.2","ccss.ela-literacy.sl.1.4","ccss.ela-literacy.sl.1.5","ccss.ela-literacy.sl.1.6","ccss.ela-literacy.w.1.1","ccss.ela-literacy.w.1.5","ccss.ela-literacy.w.1.8","ela-k2","ela-k2-cg"],"children":[{"title":"Daniel Boone and the Opening of the West","short_title":"lesson 1","hierarchy_level":"lesson","position":0,"teaser":"Students learn about Daniel Boone's contribution to opening the west.","standards":[]},{"title":"Crossing the Appalachian Mountains","short_title":"lesson 2","hierarchy_level":"lesson","position":1,"teaser":"Students learn about the Wilderness Road","standards":[]},{"title":"Jefferson and Monroe","short_title":"lesson 3","hierarchy_level":"lesson","position":2,"teaser":"Students become familiar with the geographic landmarks of the US, like the Mississippi and the Rockies.","standards":[]},{"title":"The Louisiana Purchase","short_title":"lesson 4","hierarchy_level":"lesson","position":3,"teaser":"Students understand the significance of the Louisiana Purchase","standards":[]},{"title":"Lewis and Clark","short_title":"lesson 5","hierarchy_level":"lesson","position":4,"teaser":"Students understand that there were already civilizations living in the territories of Louisiana.","standards":[]},{"title":"Lewis and Clark: The Journey Begins","short_title":"lesson 6","hierarchy_level":"lesson","position":5,"teaser":"Students learn about some of the tribes living in the territory when Lewis and Clark began their expedition.","standards":[]},{"title":"Discovery and Danger on the Prairie","short_title":"lesson 7","hierarchy_level":"lesson","position":6,"teaser":"Students learn about Lewis and Clark's encounters with Native Americans during the expedition","standards":[]},{"title":"Sacagawea","short_title":"lesson 8","hierarchy_level":"lesson","position":7,"teaser":"Students learn about Sacagawea's relationship with Lewis and Clark","standards":[]},{"title":"Red Cedars and Grizzly Bears","short_title":"lesson 9","hierarchy_level":"lesson","position":8,"teaser":"Students learn about what motivated Lewis and Clark to embark on the expedition.","standards":[]},{"title":"Rivers and Mountains","short_title":"lesson 10","hierarchy_level":"lesson","position":9,"teaser":"Students learn about how Sacagewea, Lewis and Clark worked together during the expedition.","standards":[]},{"title":"To the Pacific and Back","short_title":"lesson 11","hierarchy_level":"lesson","position":10,"teaser":"Students learn about how Sacagewea, Lewis and Clark worked together during the expedition.","standards":[]},{"title":"Domain Review","short_title":"lesson 12","hierarchy_level":"lesson","position":11,"teaser":"Review of Frontier Explorers","standards":[]},{"title":"Domain Assessment","short_title":"lesson 13","hierarchy_level":"lesson","position":12,"teaser":"Assessment of Frontier Explorers","standards":[]},{"title":"Culminating Activities","short_title":"lesson 14","hierarchy_level":"lesson","position":13,"teaser":"Culminating Activities for Frontier Explorers","standards":[]}]}]},{"title":"Core Knowledge Language Arts, Skills","short_title":"skills strand","hierarchy_level":"module","position":1,"teaser":"Students learn the decoding skills needed for reading.","standards":["ela-podcast-pk2"],"children":[{"title":"Blending and Segmenting, Tricky Words, and Spelling","short_title":"unit 1","hierarchy_level":"unit","position":0,"teaser":"Students will review sounds and spellings as well as read decodable stories from Snap Shots.","standards":["ccss.ela-literacy.l.1.1","ccss.ela-literacy.l.1.1","ccss.ela-literacy.l.1.1a","ccss.ela-literacy.l.1.1a","ccss.ela-literacy.l.1.1b","ccss.ela-literacy.l.1.1b","ccss.ela-literacy.l.1.1d","ccss.ela-literacy.l.1.1d","ccss.ela-literacy.l.1.1g","ccss.ela-literacy.l.1.1g","ccss.ela-literacy.l.1.1h","ccss.ela-literacy.l.1.1h","ccss.ela-literacy.l.1.2b","ccss.ela-literacy.l.1.2b","ccss.ela-literacy.l.1.2d","ccss.ela-literacy.l.1.2d","ccss.ela-literacy.l.1.2e","ccss.ela-literacy.l.1.2e","ccss.ela-literacy.l.1.6","ccss.ela-literacy.l.1.6","ccss.ela-literacy.rf.1.1","ccss.ela-literacy.rf.1.1","ccss.ela-literacy.rf.1.1a","ccss.ela-literacy.rf.1.1a","ccss.ela-literacy.rf.1.2b","ccss.ela-literacy.rf.1.2b","ccss.ela-literacy.rf.1.2c","ccss.ela-literacy.rf.1.2c","ccss.ela-literacy.rf.1.2d","ccss.ela-literacy.rf.1.2d","ccss.ela-literacy.rf.1.3","ccss.ela-literacy.rf.1.3","ccss.ela-literacy.rf.1.3a","ccss.ela-literacy.rf.1.3a","ccss.ela-literacy.rf.1.3b","ccss.ela-literacy.rf.1.3b","ccss.ela-literacy.rf.1.3g","ccss.ela-literacy.rf.1.3g","ccss.ela-literacy.rf.1.4a","ccss.ela-literacy.rf.1.4a","ccss.ela-literacy.rf.1.4c","ccss.ela-literacy.rf.1.4c","ccss.ela-literacy.rl.1.1","ccss.ela-literacy.rl.1.1","ccss.ela-literacy.sl.1.4","ccss.ela-literacy.sl.1.4","ccss.ela-literacy.sl.1.6","ccss.ela-literacy.sl.1.6","ela-k2","ela-k2-cg"],"children":[{"title":"Sounds /p/, /k/, /g/, /n/, /a/ Spelled ‘p’—‘P’, ‘c’—‘C’, ‘g’—‘G’, ‘n’—‘N’, ‘a’—‘A’","short_title":"lesson 1","hierarchy_level":"lesson","position":0,"teaser":"Students will work with Sounds /p/, /k/, /g/, /n/, /a/ Spelled ‘p’—‘P’, ‘c’—‘C’, ‘g’—‘G’, ‘n’—‘N’, ‘a’—‘A’","standards":[]},{"title":"Sounds /i/, /o/, /t/, /d/ Spelled ‘i’—‘I’, ‘o’—‘O’, ‘t’—‘T’, ‘d’—‘D’","short_title":"lesson 2","hierarchy_level":"lesson","position":1,"teaser":"Students will work with sounds /i/, /o/, /t/, /d/ Spelled ‘i’—‘I’, ‘o’—‘O’, ‘t’—‘T’, ‘d’—‘D’","standards":[]},{"title":"Tricky Words: a, I; Grammar: Nouns","short_title":"lesson 3","hierarchy_level":"lesson","position":2,"teaser":"Students will study tricky words and nouns","standards":[]},{"title":"Sounds /m/, /f/, /v/ Spelled ‘m’—‘M’, ‘f’—‘F’, ‘v’—‘V’","short_title":"lesson 4","hierarchy_level":"lesson","position":3,"teaser":"Students will learn the /m/, /f/, and /v/ sounds, along with their representations","standards":[]},{"title":"Sounds /s/, /z/, /h/ Spelled ‘s’—‘S’, ‘z’—‘Z’, ‘h’—‘H’; Tricky Words: no, so, of","short_title":"lesson 5","hierarchy_level":"lesson","position":4,"teaser":"Students will learn /s/, /z/, and /h/, with tricky words no, so, and of.","standards":[]},{"title":"Word Recognition Assessment","short_title":"lesson 6","hierarchy_level":"lesson","position":5,"teaser":"Students will be assessed on word recognition","standards":[]},{"title":"Reading Assessment","short_title":"lesson 7","hierarchy_level":"lesson","position":6,"teaser":"Reading assessment","standards":[]},{"title":"Reading Assessment","short_title":"lesson 8","hierarchy_level":"lesson","position":7,"teaser":"Reading assessment","standards":[]},{"title":"Reading Assessment","short_title":"lesson 9","hierarchy_level":"lesson","position":8,"teaser":"Reading assessment","standards":[]},{"title":"Reading Assessment","short_title":"lesson 10","hierarchy_level":"lesson","position":9,"teaser":"Reading assessment","standards":[]},{"title":"Sister Sounds /s/ and /z/, /f/ and /v/; Tricky Words: is, to","short_title":"lesson 11","hierarchy_level":"lesson","position":10,"teaser":"Students will learn about sister sounds /s/ and /z/; /f/ and /v/, as well as tricky words \"is\" and \"to\"","standards":[]},{"title":"Sounds /b/, /l/, /r/ Spelled ‘b’—‘B’, ‘l’—‘L’, ‘r’—‘R’","short_title":"lesson 12","hierarchy_level":"lesson","position":11,"teaser":"Students will learn /b/, /l/, and /r/","standards":[]},{"title":"Sounds /w/, /e/, /u/ Spelled ‘w’—‘W’, ‘e’—‘E’, ‘u’—‘U’; Tricky Words: all, some","short_title":"lesson 13","hierarchy_level":"lesson","position":12,"teaser":"Students will learn /w/, /e/, and /u/, with \"all\" and \"some\"","standards":[]},{"title":"Grammar: Nouns; Tricky Words: from, word","short_title":"lesson 14","hierarchy_level":"lesson","position":13,"teaser":"Students will focus on tricky words \"from\" and \"word\"","standards":[]},{"title":"Sounds /j/, /y/ Spelled ‘j’—‘J’, ‘y’—‘Y’; Tricky Words: are, have, were","short_title":"lesson 15","hierarchy_level":"lesson","position":14,"teaser":"Students will learn /j/ and /y/; \"are\" \"have\" and \"were\"","standards":[]},{"title":"Sounds /x/, /k/ Spelled ‘x’—’X’, ‘k’—’K’; Tricky Words: one, once","short_title":"lesson 16","hierarchy_level":"lesson","position":15,"teaser":"Students will learn /x/ and /k/; \"one\" and \"once\"","standards":[]},{"title":"Sounds /ch/, /sh/ Spelled ‘ch’, ‘sh’; Grammar: Nouns; Tricky Words: do, two","short_title":"lesson 17","hierarchy_level":"lesson","position":16,"teaser":"Students will learn /ch/ and /sh/; as well as \"do\" and \"two\"","standards":[]},{"title":"Sister Sounds /th/ and /th/","short_title":"lesson 18","hierarchy_level":"lesson","position":17,"teaser":"Students will learn /th/ sister sounds","standards":[]},{"title":"Tricky Words: the, who","short_title":"lesson 19","hierarchy_level":"lesson","position":18,"teaser":"Students will learn tricky words \"the\" and \"who\"","standards":[]},{"title":"Tricky Words: said, says; Sounds /ng/, /qu/ Spelled ‘ng’, ‘qu’","short_title":"lesson 20","hierarchy_level":"lesson","position":19,"teaser":"Students will learn tricky words \"said\" and \"says\"; and /ng/ and /qu/","standards":[]},{"title":"Vowel Sound Review","short_title":"lesson 21","hierarchy_level":"lesson","position":20,"teaser":"Students will review vowel sounds using mirror","standards":[]},{"title":"Vowel and Consonant Sound Review; Grammar: Nouns","short_title":"lesson 22","hierarchy_level":"lesson","position":21,"teaser":"Students will continue to review vowel sounds and consonants","standards":[]},{"title":"Sounds /k/, /b/, /d/, /f/, /g/, /l/, /m/, /s/ Spelled ‘ck’, ‘bb’, ‘dd’, ‘ff ’, ‘gg’, ‘ll’, ‘mm’, ‘ss’","short_title":"lesson 23","hierarchy_level":"lesson","position":22,"teaser":"Students will learn about double-letter spellings","standards":[]},{"title":"Sounds /k/, /n/, /p/, /r/, /t/, /z/ Spelled ‘cc’, ‘nn’, ‘pp’, ‘rr’, ‘tt’, ‘zz’;The Sound /k/ Spelled ‘c’, ‘ck’, ‘k’, ‘cc’","short_title":"lesson 24","hierarchy_level":"lesson","position":23,"teaser":"Students will focus on double letter spellings and /k/ spelled 'ck' 'k' and 'cc'","standards":[]},{"title":"Review Sister Sounds /s/ and /z/; Tricky Words: was, when, why","short_title":"lesson 25","hierarchy_level":"lesson","position":24,"teaser":"Students will continue to review sister sounds","standards":[]},{"title":"Grammar: Nouns","short_title":"lesson 26","hierarchy_level":"lesson","position":25,"teaser":"Students will spend time reading \"The Flag Shop,\" practicing their decoding.","standards":[]},{"title":"Question Mark; Tricky Words: where, which, what","short_title":"lesson 27","hierarchy_level":"lesson","position":26,"teaser":"Students will learn about question marks and tricky words beginning with \"wh\"","standards":[]},{"title":"Review","short_title":"lesson 28","hierarchy_level":"lesson","position":27,"teaser":"Students will review, reading \"Which is the Best?\"","standards":[]},{"title":"Quotation Marks; Tricky Words: here, there","short_title":"lesson 29","hierarchy_level":"lesson","position":28,"teaser":"Students will review punctuation marks and read \"The Bus Stop\"","standards":[]},{"title":"Review","short_title":"lesson 30","hierarchy_level":"lesson","position":29,"teaser":"Students will learn \"The Alphabet Song\" and read, in small groups, \"On the Bus\"","standards":[]},{"title":"Review","short_title":"lesson 31","hierarchy_level":"lesson","position":30,"teaser":"Students practice with tricky words and partner read \"The Man in the Black Hat\"","standards":[]},{"title":"Review","short_title":"lesson 32","hierarchy_level":"lesson","position":31,"teaser":"Students continue to practice with tricky words and partner read \"The Man in the Kilt\"","standards":[]}]},{"title":"Five Vowel Sounds","short_title":"unit 2","hierarchy_level":"unit","position":1,"teaser":"In Unit 2, we introduce five vowel sounds and the most common (or least ambiguous) spelling for each sound.","standards":["ccss.ela-literacy.rf.1.1","ccss.ela-literacy.rf.1.1","ccss.ela-literacy.rf.1.1a","ccss.ela-literacy.rf.1.1a","ccss.ela-literacy.rf.1.2","ccss.ela-literacy.rf.1.2","ccss.ela-literacy.rf.1.2a","ccss.ela-literacy.rf.1.2a","ccss.ela-literacy.rf.1.2b","ccss.ela-literacy.rf.1.2b","ccss.ela-literacy.rf.1.2c","ccss.ela-literacy.rf.1.2c","ccss.ela-literacy.rf.1.2d","ccss.ela-literacy.rf.1.2d","ccss.ela-literacy.rf.1.3c","ccss.ela-literacy.rf.1.3c","ccss.ela-literacy.rf.1.3g","ccss.ela-literacy.rf.1.3g","ccss.ela-literacy.rf.1.4a","ccss.ela-literacy.rf.1.4a","ccss.ela-literacy.rf.1.4b","ccss.ela-literacy.rf.1.4b","ccss.ela-literacy.rl.1.1","ccss.ela-literacy.rl.1.1","ccss.ela-literacy.rl.1.10","ccss.ela-literacy.rl.1.10","ccss.ela-literacy.rl.1.3","ccss.ela-literacy.rl.1.3","ccss.ela-literacy.rl.1.7","ccss.ela-literacy.rl.1.7","ccss.ela-literacy.sl.1.5","ccss.ela-literacy.sl.1.5","ccss.ela-literacy.sl.1.6","ccss.ela-literacy.sl.1.6","ela-k2","ela-k2-cg"],"children":[{"title":"Vowel Digraph ‘ee’","short_title":"lesson 1","hierarchy_level":"lesson","position":0,"teaser":"Students work with medial sounds and listen to a demonstration story","standards":[]},{"title":"Tricky Words; Nouns","short_title":"lesson 2","hierarchy_level":"lesson","position":1,"teaser":"Students work on noun identification and sound spelling review","standards":[]},{"title":"Vowel Digraph ‘a_e’","short_title":"lesson 3","hierarchy_level":"lesson","position":2,"teaser":"Students work with vowel digraph a_e and reread \"Grans Trips\" or \"The Pet\"","standards":[]},{"title":"Review Vowel Digraphs","short_title":"lesson 4","hierarchy_level":"lesson","position":3,"teaser":"Students review vowel digraphs and being a new story","standards":[]},{"title":"Tricky Words","short_title":"lesson 5","hierarchy_level":"lesson","position":4,"teaser":"Student work with tricky word cards and continue reading \"Wong from Hong Kong\"","standards":[]},{"title":"Vowel Digraph ‘i_e’","short_title":"lesson 6","hierarchy_level":"lesson","position":5,"teaser":"Students are introduced to a new sound and do pair reading from \"The Swim Meet\"","standards":[]},{"title":"Nouns","short_title":"lesson 7","hierarchy_level":"lesson","position":6,"teaser":"Students work with identifying proper nouns and read about the coral reef","standards":[]},{"title":"Vowel Digraph ‘o_e’","short_title":"lesson 8","hierarchy_level":"lesson","position":7,"teaser":"Students work with vowel digraphs after teacher modeling.","standards":[]},{"title":"Tricky Words","short_title":"lesson 9","hierarchy_level":"lesson","position":8,"teaser":"Students work with nouns, tricky words, and rereading \"Gran\"","standards":[]},{"title":"Nouns","short_title":"lesson 10","hierarchy_level":"lesson","position":9,"teaser":"Students work with sounds, tricky words, and \"Bug Glass\" in small groups after teacher modeling","standards":[]},{"title":"Nouns","short_title":"lesson 11","hierarchy_level":"lesson","position":10,"teaser":"Students identify nouns that name places and partner read \"The Tape\"","standards":[]},{"title":"Vowel Digraph ‘u_e’","short_title":"lesson 12","hierarchy_level":"lesson","position":11,"teaser":"Students work with vowel digraph u_e and begin \"Fuzz and Mel\" with teacher demonstration","standards":[]},{"title":"Review","short_title":"lesson 13","hierarchy_level":"lesson","position":12,"teaser":"Students work with nouns, digraph dictation, and apply it to small group reading work","standards":[]},{"title":"Tricky Words; Review","short_title":"lesson 14","hierarchy_level":"lesson","position":13,"teaser":"Students work with tricky words and revisit \"Gran\"","standards":[]},{"title":"Review","short_title":"lesson 15","hierarchy_level":"lesson","position":14,"teaser":"Students work with tricky words, spelling, and grammar and listen to \"King and Queen\"","standards":[]},{"title":"Review","short_title":"lesson 16","hierarchy_level":"lesson","position":15,"teaser":"Spelling Bee and review of tricky words and grammar","standards":[]},{"title":"Review","short_title":"lesson 17","hierarchy_level":"lesson","position":16,"teaser":"Students partner read \"The Trip West\"","standards":[]},{"title":"Review/Assessment","short_title":"lesson 18","hierarchy_level":"lesson","position":17,"teaser":"Students take a comprehension assessment","standards":[]},{"title":"Review/Assessment","short_title":"lesson 19","hierarchy_level":"lesson","position":18,"teaser":"Students take a grammar assessment and reread from \"Gran\"","standards":[]}]},{"title":"New Vowel Sounds and Spellings","short_title":"unit 3","hierarchy_level":"unit","position":2,"teaser":"Students work with five new vowel sounds and the common spellings for each sound, as well as practice their learning in decodable texts with specific emphases on those sounds.","standards":["ccss.ela-literacy.l.1.1","ccss.ela-literacy.l.1.1","ccss.ela-literacy.l.1.1a","ccss.ela-literacy.l.1.1a","ccss.ela-literacy.l.1.1b","ccss.ela-literacy.l.1.1b","ccss.ela-literacy.l.1.1d","ccss.ela-literacy.l.1.1d","ccss.ela-literacy.l.1.1e","ccss.ela-literacy.l.1.1e","ccss.ela-literacy.l.1.1g","ccss.ela-literacy.l.1.1g","ccss.ela-literacy.l.1.1h","ccss.ela-literacy.l.1.1h","ccss.ela-literacy.l.1.1j","ccss.ela-literacy.l.1.1j","ccss.ela-literacy.l.1.2","ccss.ela-literacy.l.1.2","ccss.ela-literacy.l.1.2b","ccss.ela-literacy.l.1.2b","ccss.ela-literacy.l.1.2d","ccss.ela-literacy.l.1.2d","ccss.ela-literacy.l.1.2e","ccss.ela-literacy.l.1.2e","ccss.ela-literacy.l.1.6","ccss.ela-literacy.l.1.6","ccss.ela-literacy.rf.1.2","ccss.ela-literacy.rf.1.2","ccss.ela-literacy.rf.1.2b","ccss.ela-literacy.rf.1.2b","ccss.ela-literacy.rf.1.2c","ccss.ela-literacy.rf.1.2c","ccss.ela-literacy.rf.1.2d","ccss.ela-literacy.rf.1.2d","ccss.ela-literacy.rf.1.3","ccss.ela-literacy.rf.1.3","ccss.ela-literacy.rf.1.3a","ccss.ela-literacy.rf.1.3a","ccss.ela-literacy.rf.1.3b","ccss.ela-literacy.rf.1.3b","ccss.ela-literacy.rf.1.3c","ccss.ela-literacy.rf.1.3c","ccss.ela-literacy.rf.1.3g","ccss.ela-literacy.rf.1.3g","ccss.ela-literacy.rf.1.4","ccss.ela-literacy.rf.1.4","ccss.ela-literacy.rf.1.4a","ccss.ela-literacy.rf.1.4a","ccss.ela-literacy.rf.1.4b","ccss.ela-literacy.rf.1.4b","ccss.ela-literacy.rf.1.4c","ccss.ela-literacy.rf.1.4c","ccss.ela-literacy.rl.1.1","ccss.ela-literacy.rl.1.1","ccss.ela-literacy.rl.1.10","ccss.ela-literacy.rl.1.10","ccss.ela-literacy.rl.1.3","ccss.ela-literacy.rl.1.3","ccss.ela-literacy.rl.1.5","ccss.ela-literacy.rl.1.5","ccss.ela-literacy.rl.1.7","ccss.ela-literacy.rl.1.7","ccss.ela-literacy.sl.1.4","ccss.ela-literacy.sl.1.4","ccss.ela-literacy.sl.1.5","ccss.ela-literacy.sl.1.5","ccss.ela-literacy.sl.1.6","ccss.ela-literacy.sl.1.6","ccss.ela-literacy.w.1.1","ccss.ela-literacy.w.1.1","ccss.ela-literacy.w.1.3","ccss.ela-literacy.w.1.3","ccss.ela-literacy.w.1.5","ccss.ela-literacy.w.1.5","ela-k2","ela-k2-cg"],"children":[{"title":"Sound /oo/ Spelled ‘oo’","short_title":"lesson 1","hierarchy_level":"lesson","position":0,"teaser":"Students work on spelling words and a family letter","standards":[]},{"title":"Tricky Word because; Planning a Fictional Narrative","short_title":"lesson 2","hierarchy_level":"lesson","position":1,"teaser":"Students work on spelling, dictations, tricky words, and fiction","standards":[]},{"title":"Drafting a Fictional Narrative","short_title":"lesson 3","hierarchy_level":"lesson","position":2,"teaser":"Students write a draft of a fictional narrative and continue partner reading","standards":[]},{"title":"Editing a Fictional Narrative","short_title":"lesson 4","hierarchy_level":"lesson","position":3,"teaser":"Students edit their narrative and focus on short vowel sounds","standards":[]},{"title":"Sound /oo/ Spelled ‘oo’","short_title":"lesson 5","hierarchy_level":"lesson","position":4,"teaser":"Students are assessed on spelling. They also do review of tricky words.","standards":[]},{"title":"Planning and Drafting a Book Report","short_title":"lesson 6","hierarchy_level":"lesson","position":5,"teaser":"Students learn new spelling words, and begin planning and drafting a book report","standards":[]},{"title":"Tricky Spelling ‘oo’; Editing a Book Report","short_title":"lesson 7","hierarchy_level":"lesson","position":6,"teaser":"Students review spelling and introduce tricky spelling, as well as editing their book reports","standards":[]},{"title":"Identifying Verbs; Publishing a Book Report","short_title":"lesson 8","hierarchy_level":"lesson","position":7,"teaser":"Students write their final copy and read \"The Two Mules\" in their small groups","standards":[]},{"title":"Sound /ou/ Spelled ‘ou","short_title":"lesson 9","hierarchy_level":"lesson","position":8,"teaser":"Students are introduced to a new sound and continue with \"The Two Mules\" to practice that sound","standards":[]},{"title":"Tricky Word down; Identifying Verbs","short_title":"lesson 10","hierarchy_level":"lesson","position":9,"teaser":"Students are assessed on spelling and learn about tricky verbs","standards":[]},{"title":"Review","short_title":"lesson 11","hierarchy_level":"lesson","position":10,"teaser":"Students work on spelling words and review","standards":[]},{"title":"Sound /oi/ Spelled ‘oi’","short_title":"lesson 12","hierarchy_level":"lesson","position":11,"teaser":"Students work on vowel spellings and read in small group \"The Bag of Coins\" to practice the /oi/","standards":[]},{"title":"Identifying Present- and Past-Tense Verbs","short_title":"lesson 13","hierarchy_level":"lesson","position":12,"teaser":"Students review sounds and reread Stories and Fables.","standards":[]},{"title":"Review","short_title":"lesson 14","hierarchy_level":"lesson","position":13,"teaser":"Students work with digraphs and reread from the Stories and Fables","standards":[]},{"title":"Sound /aw/ Spelled ‘aw’","short_title":"lesson 15","hierarchy_level":"lesson","position":14,"teaser":"Students are assessed on spelling and the teacher introduces the /aw/ spelled 'aw'","standards":[]},{"title":"Review","short_title":"lesson 16","hierarchy_level":"lesson","position":15,"teaser":"Students review common and proper nouns, work with verbs, and read \"The Dog and the Ox\" as a full group","standards":[]},{"title":"Review","short_title":"lesson 17","hierarchy_level":"lesson","position":16,"teaser":"Students work with digraphs and read \"The Fox and the Grapes\"","standards":[]},{"title":"Review","short_title":"lesson 18","hierarchy_level":"lesson","position":17,"teaser":"Students practice with tricky words in the stories they have been reading","standards":[]},{"title":"Word Recognition and Story Comprehension Assessments","short_title":"lesson 19","hierarchy_level":"lesson","position":18,"teaser":"Students are assessed on word recognition and read \"The Fox and the Crane\"","standards":[]}]},{"title":"Spelling, Comprehension, and Word Reading","short_title":"unit 4","hierarchy_level":"unit","position":3,"teaser":"In this unit we introduce the sounds that are sometimes called the /r/-controlled vowel sounds and the most common spelling for each sound.","standards":["ccss.ela-literacy.l.1.1","ccss.ela-literacy.l.1.1","ccss.ela-literacy.l.1.1a","ccss.ela-literacy.l.1.1a","ccss.ela-literacy.l.1.1b","ccss.ela-literacy.l.1.1b","ccss.ela-literacy.l.1.1d","ccss.ela-literacy.l.1.1d","ccss.ela-literacy.l.1.1e","ccss.ela-literacy.l.1.1e","ccss.ela-literacy.l.1.1f","ccss.ela-literacy.l.1.1f","ccss.ela-literacy.l.1.1g","ccss.ela-literacy.l.1.1g","ccss.ela-literacy.l.1.1h","ccss.ela-literacy.l.1.1h","ccss.ela-literacy.l.1.1j","ccss.ela-literacy.l.1.1j","ccss.ela-literacy.l.1.2","ccss.ela-literacy.l.1.2","ccss.ela-literacy.l.1.2a","ccss.ela-literacy.l.1.2a","ccss.ela-literacy.l.1.2b","ccss.ela-literacy.l.1.2b","ccss.ela-literacy.l.1.2c","ccss.ela-literacy.l.1.2c","ccss.ela-literacy.l.1.2d","ccss.ela-literacy.l.1.2d","ccss.ela-literacy.l.1.4","ccss.ela-literacy.l.1.4","ccss.ela-literacy.l.1.4b","ccss.ela-literacy.l.1.4b","ccss.ela-literacy.l.1.4c","ccss.ela-literacy.l.1.4c","ccss.ela-literacy.l.1.6","ccss.ela-literacy.l.1.6","ccss.ela-literacy.rf.1.1","ccss.ela-literacy.rf.1.1","ccss.ela-literacy.rf.1.1a","ccss.ela-literacy.rf.1.1a","ccss.ela-literacy.rf.1.2","ccss.ela-literacy.rf.1.2","ccss.ela-literacy.rf.1.2b","ccss.ela-literacy.rf.1.2b","ccss.ela-literacy.rf.1.2c","ccss.ela-literacy.rf.1.2c","ccss.ela-literacy.rf.1.2d","ccss.ela-literacy.rf.1.2d","ccss.ela-literacy.rf.1.3","ccss.ela-literacy.rf.1.3","ccss.ela-literacy.rf.1.3b","ccss.ela-literacy.rf.1.3b","ccss.ela-literacy.rf.1.3c","ccss.ela-literacy.rf.1.3c","ccss.ela-literacy.rf.1.3d","ccss.ela-literacy.rf.1.3d","ccss.ela-literacy.rf.1.3e","ccss.ela-literacy.rf.1.3e","ccss.ela-literacy.rf.1.3f","ccss.ela-literacy.rf.1.3f","ccss.ela-literacy.rf.1.3g","ccss.ela-literacy.rf.1.3g","ccss.ela-literacy.rf.1.4","ccss.ela-literacy.rf.1.4","ccss.ela-literacy.rf.1.4a","ccss.ela-literacy.rf.1.4a","ccss.ela-literacy.rf.1.4b","ccss.ela-literacy.rf.1.4b","ccss.ela-literacy.rf.1.4c","ccss.ela-literacy.rf.1.4c","ccss.ela-literacy.ri.1.1","ccss.ela-literacy.ri.1.1","ccss.ela-literacy.ri.1.10","ccss.ela-literacy.ri.1.10","ccss.ela-literacy.ri.1.2","ccss.ela-literacy.ri.1.2","ccss.ela-literacy.ri.1.3","ccss.ela-literacy.ri.1.3","ccss.ela-literacy.ri.1.4","ccss.ela-literacy.ri.1.4","ccss.ela-literacy.ri.1.5","ccss.ela-literacy.ri.1.5","ccss.ela-literacy.ri.1.6","ccss.ela-literacy.ri.1.6","ccss.ela-literacy.ri.1.7","ccss.ela-literacy.ri.1.7","ccss.ela-literacy.rl.1.5","ccss.ela-literacy.rl.1.5","ccss.ela-literacy.sl.1.4","ccss.ela-literacy.sl.1.4","ccss.ela-literacy.sl.1.6","ccss.ela-literacy.sl.1.6","ccss.ela-literacy.w.1.2","ccss.ela-literacy.w.1.2","ccss.ela-literacy.w.1.5","ccss.ela-literacy.w.1.5","ccss.ela-literacy.w.1.6","ccss.ela-literacy.w.1.6","ccss.ela-literacy.w.1.8","ccss.ela-literacy.w.1.8","ela-k2","ela-k2-cg"],"children":[{"title":"Sound /er/ Spelled ‘er’; Tricky Words Sunday, Monday, Tuesday, Wednesday, Thursday, Friday, Saturday","short_title":"lesson 1","hierarchy_level":"lesson","position":0,"teaser":"Students are introduced to the sound using sound riddles","standards":[]},{"title":"Contractions","short_title":"lesson 2","hierarchy_level":"lesson","position":1,"teaser":"Students work with vowel spellings, contractions, and \"Meet Vern\"","standards":[]},{"title":"Contractions","short_title":"lesson 3","hierarchy_level":"lesson","position":2,"teaser":"Student work with contractions and reread \"Meet Vern\"","standards":[]},{"title":"Sound /ar/ Spelled ‘ar’","short_title":"lesson 4","hierarchy_level":"lesson","position":3,"teaser":"Students work with the /ar/ sound and read \"Things that Swim\"","standards":[]},{"title":"Review","short_title":"lesson 5","hierarchy_level":"lesson","position":4,"teaser":"Students review and are assessed on spelling","standards":[]},{"title":"Review","short_title":"lesson 6","hierarchy_level":"lesson","position":5,"teaser":"Students engage in vowel spelling review","standards":[]},{"title":"Sound /or/ Spelled ‘or’; Two-Syllable Words","short_title":"lesson 7","hierarchy_level":"lesson","position":6,"teaser":"Students are introduced to two-syllable words","standards":[]},{"title":"Tricky Words yesterday, today, tomorrow","short_title":"lesson 8","hierarchy_level":"lesson","position":7,"teaser":"Students practice with two-syllable words and tricky words","standards":[]},{"title":"Review and Practice","short_title":"lesson 9","hierarchy_level":"lesson","position":8,"teaser":"Students work with two-syllable words, identify nouns and verbs, and reread \"Chimps\" in small groups","standards":[]},{"title":"Review","short_title":"lesson 10","hierarchy_level":"lesson","position":9,"teaser":"Students work with spelling and listen to a whole-group reading of \"Mandrills\"","standards":[]},{"title":"Review","short_title":"lesson 11","hierarchy_level":"lesson","position":10,"teaser":"Students work with present and past tense verbs","standards":[]},{"title":"Review","short_title":"lesson 12","hierarchy_level":"lesson","position":11,"teaser":"Students read \"Things with Wings\" and do vowel spelling review","standards":[]},{"title":"Identifying Past-, Present-, and Future-Tense Verbs","short_title":"lesson 13","hierarchy_level":"lesson","position":12,"teaser":"Students work specifically with past, present and future tense verbs","standards":[]},{"title":"Review","short_title":"lesson 14","hierarchy_level":"lesson","position":13,"teaser":"Students continue to work with vowel sounds, two-syllable words and reread \"Big Cats\"","standards":[]},{"title":"Review","short_title":"lesson 15","hierarchy_level":"lesson","position":14,"teaser":"Students are assessed on spelling and practice \"Groundhogs\"","standards":[]},{"title":"Review","short_title":"lesson 16","hierarchy_level":"lesson","position":15,"teaser":"Students work with \"ed\" and then whole-group read \"The Reptile Room\"","standards":[]},{"title":"Adjectives","short_title":"lesson 17","hierarchy_level":"lesson","position":16,"teaser":"Students work with adjectives in addition to nouns and verbs","standards":[]},{"title":"Review and Practice","short_title":"lesson 18","hierarchy_level":"lesson","position":17,"teaser":"Students use adjectives and practice verb identification","standards":[]},{"title":"Review","short_title":"lesson 19","hierarchy_level":"lesson","position":18,"teaser":"Students word-sort and partner read \"Termite\"","standards":[]},{"title":"Planning a Descriptive Paragraph","short_title":"lesson 20","hierarchy_level":"lesson","position":19,"teaser":"Students begin planning a descriptive paragraph","standards":[]},{"title":"Drafting a Descriptive Paragraph","short_title":"lesson 21","hierarchy_level":"lesson","position":20,"teaser":"Students draft a descriptive paragraph using what they have learned about nouns, adjectives and verbs.","standards":[]},{"title":"Planning and Researching a Descriptive Paragraph","short_title":"lesson 22","hierarchy_level":"lesson","position":21,"teaser":"Students plan and research using informational text","standards":[]},{"title":"Drafting a Descriptive Paragraph","short_title":"lesson 23","hierarchy_level":"lesson","position":22,"teaser":"Students draft their writing and read in small groups \"Cranes and Spoonbills\"","standards":[]},{"title":"Editing a Descriptive Paragraph","short_title":"lesson 24","hierarchy_level":"lesson","position":23,"teaser":"Students will edit their descriptive writing using what they have learned about grammar and format","standards":[]},{"title":"End-of-Unit Assessment","short_title":"lesson 25","hierarchy_level":"lesson","position":24,"teaser":"Students will do the assessment and do some reading.","standards":[]},{"title":"Mid-Year Assessment","short_title":"lesson 26","hierarchy_level":"lesson","position":25,"teaser":"Students will be assessed on reading comprehension and word reading in isolation","standards":[]},{"title":"Mid-Year Assessment","short_title":"lesson 27","hierarchy_level":"lesson","position":26,"teaser":"The assessment will continue around reading comprehension and word reading","standards":[]},{"title":"Mid-Year Assessment","short_title":"lesson 28","hierarchy_level":"lesson","position":27,"teaser":"Students will be assessed on reading comprehension and word reading in isolation","standards":[]}]},{"title":"Spelling Alternatives and Advancing the Code","short_title":"unit 5","hierarchy_level":"unit","position":4,"teaser":"Students move from the clear spelling of sounds to the more advanced codes.","standards":["ccss.ela-literacy.l.1.1","ccss.ela-literacy.l.1.1","ccss.ela-literacy.l.1.1a","ccss.ela-literacy.l.1.1a","ccss.ela-literacy.l.1.1b","ccss.ela-literacy.l.1.1b","ccss.ela-literacy.l.1.1e","ccss.ela-literacy.l.1.1e","ccss.ela-literacy.l.1.1f","ccss.ela-literacy.l.1.1f","ccss.ela-literacy.l.1.1i","ccss.ela-literacy.l.1.1i","ccss.ela-literacy.l.1.1j","ccss.ela-literacy.l.1.1j","ccss.ela-literacy.l.1.2","ccss.ela-literacy.l.1.2","ccss.ela-literacy.l.1.2a","ccss.ela-literacy.l.1.2a","ccss.ela-literacy.l.1.2b","ccss.ela-literacy.l.1.2b","ccss.ela-literacy.l.1.2c","ccss.ela-literacy.l.1.2c","ccss.ela-literacy.l.1.2d","ccss.ela-literacy.l.1.2d","ccss.ela-literacy.l.1.2e","ccss.ela-literacy.l.1.2e","ccss.ela-literacy.l.1.4","ccss.ela-literacy.l.1.4","ccss.ela-literacy.l.1.4a","ccss.ela-literacy.l.1.4a","ccss.ela-literacy.l.1.4b","ccss.ela-literacy.l.1.4b","ccss.ela-literacy.l.1.4c","ccss.ela-literacy.l.1.4c","ccss.ela-literacy.l.1.6","ccss.ela-literacy.l.1.6","ccss.ela-literacy.rf.1.1","ccss.ela-literacy.rf.1.1","ccss.ela-literacy.rf.1.1a","ccss.ela-literacy.rf.1.1a","ccss.ela-literacy.rf.1.2","ccss.ela-literacy.rf.1.2","ccss.ela-literacy.rf.1.2b","ccss.ela-literacy.rf.1.2b","ccss.ela-literacy.rf.1.2c","ccss.ela-literacy.rf.1.2c","ccss.ela-literacy.rf.1.3","ccss.ela-literacy.rf.1.3","ccss.ela-literacy.rf.1.3b","ccss.ela-literacy.rf.1.3b","ccss.ela-literacy.rf.1.3d","ccss.ela-literacy.rf.1.3d","ccss.ela-literacy.rf.1.3e","ccss.ela-literacy.rf.1.3e","ccss.ela-literacy.rf.1.3f","ccss.ela-literacy.rf.1.3f","ccss.ela-literacy.rf.1.3g","ccss.ela-literacy.rf.1.3g","ccss.ela-literacy.rf.1.4","ccss.ela-literacy.rf.1.4","ccss.ela-literacy.rf.1.4a","ccss.ela-literacy.rf.1.4a","ccss.ela-literacy.rf.1.4b","ccss.ela-literacy.rf.1.4b","ccss.ela-literacy.rf.1.4c","ccss.ela-literacy.rf.1.4c","ccss.ela-literacy.rl.1.1","ccss.ela-literacy.rl.1.1","ccss.ela-literacy.rl.1.10","ccss.ela-literacy.rl.1.10","ccss.ela-literacy.rl.1.6","ccss.ela-literacy.rl.1.6","ccss.ela-literacy.rl.1.7","ccss.ela-literacy.rl.1.7","ccss.ela-literacy.sl.1.6","ccss.ela-literacy.sl.1.6","ccss.ela-literacy.w.1.1","ccss.ela-literacy.w.1.1","ccss.ela-literacy.w.1.5","ccss.ela-literacy.w.1.5","ccss.ela-literacy.w.1.6","ccss.ela-literacy.w.1.6","ela-k2","ela-k2-cg"],"children":[{"title":"Spelling Alternatives ‘p’ and ‘pp’ for /p/","short_title":"lesson 1","hierarchy_level":"lesson","position":0,"teaser":"Students work with plural noun and the sound for /p/","standards":[]},{"title":"Tricky Word how","short_title":"lesson 2","hierarchy_level":"lesson","position":1,"teaser":"Students work with the tricky word \"how\" and read as a whole group \"A Letter from Kate\"","standards":[]},{"title":"Spelling Alternatives ‘b’ and ‘bb’ for /b/","short_title":"lesson 3","hierarchy_level":"lesson","position":2,"teaser":"Students work with the sister sounds /b/ and /p/","standards":[]},{"title":"Spelling Alternatives ‘c’, ‘k’, ‘cc’, and ‘ck’ for /k/","short_title":"lesson 4","hierarchy_level":"lesson","position":3,"teaser":"Students work with spellings for /k/ and apply that to \"In the Cave\"","standards":[]},{"title":"Spelling Alternatives ‘c’, ‘k’, ‘cc’, and ‘ck’ for /k/","short_title":"lesson 5","hierarchy_level":"lesson","position":4,"teaser":"Students are assessed for spelling with attention to the /k/ sound","standards":[]},{"title":"Spelling Alternatives ‘ch’ and ‘tch’ for /ch/","short_title":"lesson 6","hierarchy_level":"lesson","position":5,"teaser":"Students are introduced to spellings for /ch/ and \"The Coin Shop\"","standards":[]},{"title":"Spelling Alternatives ‘g’ and ‘gg’ for /g/","short_title":"lesson 7","hierarchy_level":"lesson","position":6,"teaser":"Students work with spellings for /g/ and \"The Coin Shop\"","standards":[]},{"title":"Spelling Alternatives ‘j’, ‘g’, and ‘ge’ for /j/","short_title":"lesson 8","hierarchy_level":"lesson","position":7,"teaser":"Students are working with /j/ and partner reading for \"You Never Can Tell\"","standards":[]},{"title":"Tricky Spelling ‘g’ for /g/ and /j/","short_title":"lesson 9","hierarchy_level":"lesson","position":8,"teaser":"Students work with the tricky spelling 'g' and \"The Offer\"","standards":[]},{"title":"Review and Practice","short_title":"lesson 10","hierarchy_level":"lesson","position":9,"teaser":"Students review spellings and work in small groups on \"The Campsite\"","standards":[]},{"title":"Spelling Alternatives ‘t’, ‘tt’, and ‘ed’ for /t/","short_title":"lesson 11","hierarchy_level":"lesson","position":10,"teaser":"Students are introduced to spellings for /t/ and the difference between statements, questions, and exclamations","standards":[]},{"title":"Spelling Alternatives ‘d’, ‘dd’, and ‘ed’ for /d/; Tricky Word stagecoach","short_title":"lesson 12","hierarchy_level":"lesson","position":11,"teaser":"Students work with sister sounds /t/ and /d/ and \"Jack's Tale\" in small groups","standards":[]},{"title":"Spelling Alternatives ‘f’ and ‘ff ’ for /f/","short_title":"lesson 13","hierarchy_level":"lesson","position":12,"teaser":"Students work with /f/ should and continue with difference between statements, questions, and exclamations","standards":[]},{"title":"Spelling Alternatives ‘v’ and ‘ve’ for /v/; Tricky Word picture","short_title":"lesson 14","hierarchy_level":"lesson","position":13,"teaser":"Students work with /f/ and /v/ and alternative spellings","standards":[]},{"title":"Introduction to Opinion Writing","short_title":"lesson 15","hierarchy_level":"lesson","position":14,"teaser":"Students are assessed on spelling and then are introduced to opinion writing","standards":[]},{"title":"Spelling Alternatives ‘r’, ‘rr’, and ‘wr’ for /r/; Planning and Drafting an Opinion Paragraph as a Class","short_title":"lesson 16","hierarchy_level":"lesson","position":15,"teaser":"Students work on planning and drafting the opinion piece as a class","standards":[]},{"title":"Planning and Drafting an Opinion Paragraph Independently","short_title":"lesson 17","hierarchy_level":"lesson","position":16,"teaser":"Students work on planning and drafting the opinion piece independently, and also read \"Bone Man\"","standards":[]},{"title":"Editing an Opinion Paragraph","short_title":"lesson 18","hierarchy_level":"lesson","position":17,"teaser":"Students work on sentence building and editing","standards":[]},{"title":"Spelling Alternatives ‘l’ and ‘ll’ for /l/","short_title":"lesson 19","hierarchy_level":"lesson","position":18,"teaser":"Students continue with sentence building and focus on alternatives for /l/","standards":[]},{"title":"Review and Practice","short_title":"lesson 20","hierarchy_level":"lesson","position":19,"teaser":"Students review tricky words, adjectives, and partner read \"Two good things...\"","standards":[]},{"title":"Review and Practice","short_title":"lesson 21","hierarchy_level":"lesson","position":20,"teaser":"Students review two-syllable words and partner read \"The Big Dig\"","standards":[]},{"title":"End-of-Unit Assessment","short_title":"lesson 22","hierarchy_level":"lesson","position":21,"teaser":"Students are assessed on word recognition and grammar","standards":[]}]},{"title":"Spelling Alternatives for Consonant Sounds","short_title":"unit 6","hierarchy_level":"unit","position":5,"teaser":"In this unit students continue the work they began in the last unit by introducing or reviewing a number of spelling alternatives for consonant sounds.","standards":["ccss.ela-literacy.l.1.1","ccss.ela-literacy.l.1.1","ccss.ela-literacy.l.1.1a","ccss.ela-literacy.l.1.1a","ccss.ela-literacy.l.1.1b","ccss.ela-literacy.l.1.1b","ccss.ela-literacy.l.1.1d","ccss.ela-literacy.l.1.1d","ccss.ela-literacy.l.1.1e","ccss.ela-literacy.l.1.1e","ccss.ela-literacy.l.1.1f","ccss.ela-literacy.l.1.1f","ccss.ela-literacy.l.1.1g","ccss.ela-literacy.l.1.1g","ccss.ela-literacy.l.1.1h","ccss.ela-literacy.l.1.1h","ccss.ela-literacy.l.1.1i","ccss.ela-literacy.l.1.1i","ccss.ela-literacy.l.1.1j","ccss.ela-literacy.l.1.1j","ccss.ela-literacy.l.1.2","ccss.ela-literacy.l.1.2","ccss.ela-literacy.l.1.2a","ccss.ela-literacy.l.1.2a","ccss.ela-literacy.l.1.2b","ccss.ela-literacy.l.1.2b","ccss.ela-literacy.l.1.2c","ccss.ela-literacy.l.1.2c","ccss.ela-literacy.l.1.2d","ccss.ela-literacy.l.1.2d","ccss.ela-literacy.l.1.2e","ccss.ela-literacy.l.1.2e","ccss.ela-literacy.l.1.4","ccss.ela-literacy.l.1.4","ccss.ela-literacy.l.1.4a","ccss.ela-literacy.l.1.4a","ccss.ela-literacy.l.1.4c","ccss.ela-literacy.l.1.4c","ccss.ela-literacy.l.1.6","ccss.ela-literacy.l.1.6","ccss.ela-literacy.rf.1.2d","ccss.ela-literacy.rf.1.2d","ccss.ela-literacy.rf.1.3","ccss.ela-literacy.rf.1.3","ccss.ela-literacy.rf.1.3b","ccss.ela-literacy.rf.1.3b","ccss.ela-literacy.rf.1.3d","ccss.ela-literacy.rf.1.3d","ccss.ela-literacy.rf.1.3e","ccss.ela-literacy.rf.1.3e","ccss.ela-literacy.rf.1.3f","ccss.ela-literacy.rf.1.3f","ccss.ela-literacy.rf.1.3g","ccss.ela-literacy.rf.1.3g","ccss.ela-literacy.rf.1.4","ccss.ela-literacy.rf.1.4","ccss.ela-literacy.rf.1.4a","ccss.ela-literacy.rf.1.4a","ccss.ela-literacy.rf.1.4c","ccss.ela-literacy.rf.1.4c","ccss.ela-literacy.rl.1.1","ccss.ela-literacy.rl.1.1","ccss.ela-literacy.rl.1.10","ccss.ela-literacy.rl.1.10","ccss.ela-literacy.sl.1.4","ccss.ela-literacy.sl.1.4","ccss.ela-literacy.sl.1.6","ccss.ela-literacy.sl.1.6","ccss.ela-literacy.w.1.3","ccss.ela-literacy.w.1.3","ccss.ela-literacy.w.1.5","ccss.ela-literacy.w.1.5","ccss.ela-literacy.w.1.6","ccss.ela-literacy.w.1.6","ela-k2","ela-k2-cg"],"children":[{"title":"Spelling Alternative ‘c’ for /s/; Introduction to Personal Narratives","short_title":"lesson 1","hierarchy_level":"lesson","position":0,"teaser":"Students begin spelling word work and are introduced to the Personal Narrative","standards":[]},{"title":"Tricky Spelling ‘c’ for /s/ and /k/; Planning a Class Personal Narrative","short_title":"lesson 2","hierarchy_level":"lesson","position":1,"teaser":"Students work with the tricky spelling 'c' and plan a class personal narrative","standards":[]},{"title":"Practice; Drafting a Class Personal Narrative","short_title":"lesson 3","hierarchy_level":"lesson","position":2,"teaser":"Students work as a class to draft a personal narrative","standards":[]},{"title":"Spelling Alternatives ‘ce’ and ‘se’ for /s/; Planning and Drafting Student Personal Narratives","short_title":"lesson 4","hierarchy_level":"lesson","position":3,"teaser":"Students are introduced to spelling alternatives for /s/ and begin planning and drafting personal narratives","standards":[]},{"title":"Practice; Editing and Publishing Personal Narratives","short_title":"lesson 5","hierarchy_level":"lesson","position":4,"teaser":"Students work on editing and publishing their narratives","standards":[]},{"title":"Review and Practice","short_title":"lesson 6","hierarchy_level":"lesson","position":5,"teaser":"Students read as a whole group \"Mister Spencer and the Rabbits\"","standards":[]},{"title":"Replacing Nouns with Pronouns","short_title":"lesson 7","hierarchy_level":"lesson","position":6,"teaser":"Students work with nouns and pronouns and do small group reading","standards":[]},{"title":"Review and Practice","short_title":"lesson 8","hierarchy_level":"lesson","position":7,"teaser":"Students work with tricky spelling 'g' and review alternatives for /j/","standards":[]},{"title":"Building Sentences with Adjectives and Prepositions","short_title":"lesson 9","hierarchy_level":"lesson","position":8,"teaser":"Students work with nouns and pronouns, then small group reading of \"Ants\"","standards":[]},{"title":"Spelling Alternative ‘kn’ for /n/","short_title":"lesson 10","hierarchy_level":"lesson","position":9,"teaser":"Students read with alternative spellings for /n/ and reread \"The Band\"","standards":[]},{"title":"Review and Practice","short_title":"lesson 11","hierarchy_level":"lesson","position":10,"teaser":"Students do a word sort and small group rereads of \"The Yard Sale\"","standards":[]},{"title":"Review and Practice","short_title":"lesson 12","hierarchy_level":"lesson","position":11,"teaser":"Students work with tricky words and pronoun review","standards":[]},{"title":"Review and Practice","short_title":"lesson 13","hierarchy_level":"lesson","position":12,"teaser":"Students work with small groups to read \"Dark Clouds and Wind\"","standards":[]},{"title":"Review and Practice","short_title":"lesson 14","hierarchy_level":"lesson","position":13,"teaser":"Students work to build sentences with adjectives and prepositions","standards":[]},{"title":"Review and Practice","short_title":"lesson 15","hierarchy_level":"lesson","position":14,"teaser":"Students take a spelling assessment, review plural nouns, and partner read \"The Visit\"","standards":[]},{"title":"Spelling Alternative ‘wh’ for /w/","short_title":"lesson 16","hierarchy_level":"lesson","position":15,"teaser":"Students work with alternatives to spelling for /w/ and read \"The Soccer Game\" in small groups","standards":[]},{"title":"Review and Practice","short_title":"lesson 17","hierarchy_level":"lesson","position":16,"teaser":"Students partner read \"Supper\"","standards":[]},{"title":"Spelling Alternative ‘n’ for /ng/","short_title":"lesson 18","hierarchy_level":"lesson","position":17,"teaser":"Students work with alternative spellings for /ng/ and read \"Grace the Performer\" in small groups","standards":[]},{"title":"Tricky Spelling ‘n’ for /n/ and /ng/","short_title":"lesson 19","hierarchy_level":"lesson","position":18,"teaser":"Students work with tricky spelling 'n'  and continue with \"Grace the Performer\"","standards":[]},{"title":"Review and Practice","short_title":"lesson 20","hierarchy_level":"lesson","position":19,"teaser":"Students read \"The Frog Jumping Contest\" and review pronouns","standards":[]},{"title":"Review and Practice","short_title":"lesson 21","hierarchy_level":"lesson","position":20,"teaser":"Students work with root words and endings as well as reading in small groups","standards":[]},{"title":"Review and Practice","short_title":"lesson 22","hierarchy_level":"lesson","position":21,"teaser":"Students work with vowel digraphs and small group reading of \"Buster the Pig\"","standards":[]},{"title":"Tricky Word cow","short_title":"lesson 23","hierarchy_level":"lesson","position":22,"teaser":"Students small group read \"Whisper\"","standards":[]},{"title":"Assessment","short_title":"lesson 24","hierarchy_level":"lesson","position":23,"teaser":"Students are assessed on word recognition and small group read \"The Harvest\"","standards":[]},{"title":"Assessment","short_title":"lesson 25","hierarchy_level":"lesson","position":24,"teaser":"Students are assessed on story comprehension","standards":[]}]},{"title":"Advanced Code and Spelling Alternatives for Vowels","short_title":"unit 7","hierarchy_level":"unit","position":6,"teaser":"Students will continue with the advanced code while focusing on spelling alternatives for vowel sounds.","standards":["ccss.ela-literacy.l.1.1","ccss.ela-literacy.l.1.1a","ccss.ela-literacy.l.1.1b","ccss.ela-literacy.l.1.1c","ccss.ela-literacy.l.1.1d","ccss.ela-literacy.l.1.1e","ccss.ela-literacy.l.1.1g","ccss.ela-literacy.l.1.1h","ccss.ela-literacy.l.1.1j","ccss.ela-literacy.l.1.2","ccss.ela-literacy.l.1.2b","ccss.ela-literacy.l.1.2c","ccss.ela-literacy.l.1.2d","ccss.ela-literacy.l.1.2e","ccss.ela-literacy.l.1.4c","ccss.ela-literacy.l.1.6","ccss.ela-literacy.rf.1.2","ccss.ela-literacy.rf.1.2b","ccss.ela-literacy.rf.1.2d","ccss.ela-literacy.rf.1.3","ccss.ela-literacy.rf.1.3b","ccss.ela-literacy.rf.1.3e","ccss.ela-literacy.rf.1.3f","ccss.ela-literacy.rf.1.3g","ccss.ela-literacy.rf.1.4","ccss.ela-literacy.rf.1.4a","ccss.ela-literacy.rf.1.4b","ccss.ela-literacy.rf.1.4c","ccss.ela-literacy.rl.1.1","ccss.ela-literacy.rl.1.10","ccss.ela-literacy.rl.1.9","ccss.ela-literacy.sl.1.6","ccss.ela-literacy.w.1.2","ccss.ela-literacy.w.1.5","ela-k2","ela-k2-cg"],"children":[{"title":"Spelling Alternatives for /ae/","short_title":"lesson 1","hierarchy_level":"lesson","position":0,"teaser":"Students work with alternative spellings for /ae/","standards":[]},{"title":"Review and Practice","short_title":"lesson 2","hierarchy_level":"lesson","position":1,"teaser":"Students read as a whole group \"Martez, Martez, Martez\"","standards":[]},{"title":"Grammar: Nouns and Verbs","short_title":"lesson 3","hierarchy_level":"lesson","position":2,"teaser":"Students review grammar and read \"Martez, Martez, Martez\" in small groups","standards":[]},{"title":"Grammar: Conjunctions; Noun-Verb Agreement","short_title":"lesson 4","hierarchy_level":"lesson","position":3,"teaser":"Students work with noun-verb agreement and read \"Dinner with Kay\"","standards":[]},{"title":"Review and Practice","short_title":"lesson 5","hierarchy_level":"lesson","position":4,"teaser":"Students read in small groups \"The Red Dish\"","standards":[]},{"title":"Grammar: Noun-Verb Agreement","short_title":"lesson 6","hierarchy_level":"lesson","position":5,"teaser":"Students work with noun-verb agreement and reread \"The Red Dish\"","standards":[]},{"title":"Grammar: Commas in a Series","short_title":"lesson 7","hierarchy_level":"lesson","position":6,"teaser":"Students work with commas in a series and partner read \"In the Mail\"","standards":[]},{"title":"Grammar: Building Sentences with Conjunctions","short_title":"lesson 8","hierarchy_level":"lesson","position":7,"teaser":"Students review root words and word endings and reread \"The Holiday\"","standards":[]},{"title":"Review and Practice","short_title":"lesson 9","hierarchy_level":"lesson","position":8,"teaser":"Students review punctuation and partner read \"Better than the Best\"","standards":[]},{"title":"Review and Practice","short_title":"lesson 10","hierarchy_level":"lesson","position":9,"teaser":"Students take a spelling assessment and then work with punctuation","standards":[]},{"title":"Spelling Alternatives for /oe/","short_title":"lesson 11","hierarchy_level":"lesson","position":10,"teaser":"Students work with /oe/ alternatives then small-group read \"The Long Cab Ride\"","standards":[]},{"title":"Grammar: Building Sentences with Conjunctions","short_title":"lesson 12","hierarchy_level":"lesson","position":11,"teaser":"Students will small group read \"The Vote\"","standards":[]},{"title":"Introduction to Instructional Writing","short_title":"lesson 13","hierarchy_level":"lesson","position":12,"teaser":"Students will whole group read \"Mister Gomez\" and work with instructional writing","standards":[]},{"title":"Instructional Writing: Sequencing Steps","short_title":"lesson 14","hierarchy_level":"lesson","position":13,"teaser":"Students will work with sequencing steps in instructional writing and small group read \"A House in the Clouds\"","standards":[]},{"title":"Instructional Writing: Giving Good Oral Instructions","short_title":"lesson 15","hierarchy_level":"lesson","position":14,"teaser":"Students will take a spelling assessment and small group read \"A House in the Clouds\"","standards":[]},{"title":"Instructional Writing: Planning and Drafting","short_title":"lesson 16","hierarchy_level":"lesson","position":15,"teaser":"Students will work on planning and drafting and read \"The Market\"","standards":[]},{"title":"Instructional Writing: Editing and Publishing","short_title":"lesson 17","hierarchy_level":"lesson","position":16,"teaser":"Students will work with editing and publishing their writing and small-group read \"A Rainforest Ride\"","standards":[]},{"title":"Review and Practice","short_title":"lesson 18","hierarchy_level":"lesson","position":17,"teaser":"Students will work with commands and small group reading","standards":[]},{"title":"End-of-Year Assessment","short_title":"lesson 19","hierarchy_level":"lesson","position":18,"teaser":"Students will complete the EOY Assessment focusing on Reading Comprehension","standards":[]},{"title":"End-of-Year Assessment","short_title":"lesson 20","hierarchy_level":"lesson","position":19,"teaser":"Students will complete the EOY Assessment focusing on fluency","standards":[]},{"title":"End-of-Year Assessment","short_title":"lesson 21","hierarchy_level":"lesson","position":20,"teaser":"Students will complete the EOY Assessment focusing on Reading in Isolation","standards":[]}]}]}]}
